Workbook

Sheet Given Balance Sheet
A1: ADEPT
A2: BALANCE SHEET
B4: 2007 | C4: 2006 | D4: 2005
A5: ASSETS
A6: Current Assets
A7: Cash | B7: 0 | C7: 0 | D7: 0
A8: Accounts Receivable | B8: 132613 | C8: 92791 | D8: 77794
A9: Prepaids | B9: 4388 | C9: 3483 | D9: 2075
A10: Inventory | B10: 19908 | C10: 17943 | D10: 20281
A11: Total Current Assets | B11: =SUM(B7:B10) -> 156909 | C11: =SUM(C7:C10) -> 114217 | D11: =SUM(D7:D10) -> 100150
A13: Net Capital Assets | B13: 92948 | C13: 60287 | D13: 68794
A15: Total Assets | B15: =B11+B13 -> 249857 | C15: =C11+C13 -> 174504 | D15: =D11+D13 -> 168944
A17: LIABILITIES & SHAREHOLDERS' EQUITY
A18: Current Liabilities
A19: Operating Line of Credit | B19: 34327 | C19: 43078 | D19: 63565
A20: Accounts Payable | B20: 113250 | C20: 65944 | D20: 70227
A21: Accrued Liabilities & Other Current Payables | B21: 5575 | C21: 6248 | D21: 6020
A22: Total Current Liabilities | B22: =SUM(B19:B21) -> 153152 | C22: =SUM(C19:C21) -> 115270 | D22: =SUM(D19:D21) -> 139812
A24: Long-Term Liabilities
A25: Sodrox Term Loan | B25: 88000 | C25: 100000 | D25: 100000
A26: Shareholder Loan | B26: 45000 | C26: 45000 | D26: =C26 -> 45000
A27: Personal Loan | B27: 42240 | C27: 35000 | D27: =C27 -> 35000
A28: Total Long-term Liabilities | B28: =SUM(B25:B27) -> 175240 | C28: =SUM(C25:C27) -> 180000 | D28: =SUM(D25:D27) -> 180000
A30: Total Liabilities | B30: =B22+B28 -> 328392 | C30: =C22+C28 -> 295270 | D30: =D22+D28 -> 319812
A32: Shareholders' Equity
A33: Capital Stock | B33: 120000 | C33: 120000 | D33: 120000
A34: Retained Earnings | B34: -198535 | C34: -240766 | D34: -270868
A35: Total Shareholders' Equity | B35: =B33+B34 -> -78535 | C35: =SUM(C33:C34) -> -120766 | D35: =D33+D34 -> -150868
A37: Total Liabilities & Shareholders' Equity | B37: =B30+B35 -> 249857 | C37: =C30+C35 -> 174504 | D37: =D30+D35 -> 168944

Sheet Cash Flows
A1: ADEPT
A3: Net Income | C3: 42231
A5: Operating Activities
A6: Amortization | B6: 10990 | E6: Retained Earnings
A7: Accounts Receivable | B7: ='Given Balance Sheet'!C8-'Given Balance Sheet'!B8 -> -39822 | E7: 240766 | F7: O/B
A8: Prepaids | B8: ='Given Balance Sheet'!C9-'Given Balance Sheet'!B9 -> -905 | E8: N/I | F8: =C3 -> 42231
A9: Inventory | B9: ='Given Balance Sheet'!C10-'Given Balance Sheet'!B10 -> -1965 | E9: =E7-F8 -> 198535 | F9: E/B
A10: Operating Line of Credit | B10: ='Given Balance Sheet'!B19-'Given Balance Sheet'!C19 -> -8751
A11: Accounts Payable | B11: ='Given Balance Sheet'!B20-'Given Balance Sheet'!C20 -> 47306
A12: Accrued Liabilities and Other Current Payables | B12: ='Given Balance Sheet'!B21-'Given Balance Sheet'!C21 -> -673 | C12: =SUM(B6:B12) -> 6180
A14: Net Cash Flow From Operations | C14: =C3+C12 -> 48411
A16: Financing Activities
A17: Sodrox Term Loan | B17: ='Given Balance Sheet'!B25-'Given Balance Sheet'!C25 -> -12000 | E17: Fixed Assets
A18: Shareholder Loan | B18: ='Given Balance Sheet'!B26-'Given Balance Sheet'!C26 -> 0 | E18: 60287 | F18: O/B
A19: Personal Loan | B19: ='Given Balance Sheet'!B27-'Given Balance Sheet'!C27 -> 7240 | E19: Dep'n | F19: =B6 -> 10990
A20: Capital Stock | B20: ='Given Balance Sheet'!C33-'Given Balance Sheet'!B33 -> 0 | E20: =E18-F19 -> 49297 | F20: T/B
A21: Dividends Declared | B21: 0 | C21: =SUM(B17:B21) -> -4760 | E21: =E22-E20 -> 43651 | F21: Purchases
E22: 92948 | F22: E/B
A23: Investing Activities
A24: Fixed Asset Purchases | C24: =-E21 -> -43651
A26: Net Cash Flow | C26: =C14+C21+C24 -> 0
A27: Beginning Cash | C27: 0
A28: Ending Cash | C28: =C26+C27 -> 0

Sheet Cash Budget
A1: ADEPT
A3: HIGHER DEAL
C4: July | D4: August | E4: September | F4: October | G4: November | H4: December | I4: Totals | M4: Average Daily Sales | O4: Age of A/R
A5: CASH INFLOWS | M5: =(250000*12)/360 -> 8333.3333 | O5: 55.5 days
A6: Sales | B6: 250,000/mo | D6: =M5*4.5 -> 37500 | E6: =$M$5*30 -> 250000 | F6: =$M$5*30 -> 250000 | G6: =$M$5*30 -> 250000 | H6: =$M$5*30 -> 250000 | I6: =SUM(C6:H6) -> 1037500
M7: August will receive 4.5 days of sales (60 days-55.5 days)
A8: Cash Outflows
A9: Operating Outflows:
A10: Salaries | B10: 40,000/year | C10: =40000/12 -> 3333.3333 | D10: =40000/12 -> 3333.3333 | E10: =40000/12 -> 3333.3333 | F10: =40000/12 -> 3333.3333 | G10: =40000/12 -> 3333.3333 | H10: =40000/12 -> 3333.3333 | I10: =SUM(C10:H10) -> 20000 | M10: Average Daily COGS | O10: Age of A/P
A11: Car Allowance | B11: 10,200/year | C11: =10200/12 -> 850 | D11: =10200/12 -> 850 | E11: =10200/12 -> 850 | F11: =10200/12 -> 850 | G11: =10200/12 -> 850 | H11: =10200/12 -> 850 | I11: =SUM(C11:H11) -> 5100 | M11: =(250000*12)*0.37/360 -> 3083.3333 | O11: 60 days
A12: Maintenance Costs | B12: 9,600/year | C12: =9600/12 -> 800 | D12: =9600/12 -> 800 | E12: =9600/12 -> 800 | F12: =9600/12 -> 800 | G12: =9600/12 -> 800 | H12: =9600/12 -> 800 | I12: =SUM(C12:H12) -> 4800
A13: COGS | E13: =$M$11*30 -> 92500 | F13: =$M$11*30 -> 92500 | G13: =$M$11*30 -> 92500 | H13: =$M$11*30 -> 92500 | I13: =SUM(C13:H13) -> 370000 | M13: September will need to pay for 60 days of inventory
A14: Investment Outflows: | M14: (month to keep in inventory and July's used inventory)
A15: Equipment | B15: 30,000/plant | C15: =30000*9 -> 270000 | I15: =SUM(C15:H15) -> 270000
A16: Inventory | E16: =M11*30 -> 92500 | I16: =SUM(C16:H16) -> 92500
A17: Total Outflows | C17: =SUM(C10:C16) -> 274983.33 | D17: =SUM(D10:D16) -> 4983.3333 | E17: =SUM(E10:E16) -> 189983.33 | F17: =SUM(F10:F16) -> 97483.333 | G17: =SUM(G10:G16) -> 97483.333 | H17: =SUM(H10:H16) -> 97483.333 | I17: =SUM(I10:I16) -> 762400
A19: Beginning Cash | C19: 0 | D19: =C21 -> -274983.33 | E19: =D21 -> -242466.67 | F19: =E21 -> -182450 | G19: =F21 -> -29933.333 | H19: =G21 -> 122583.33
A20: Net Cash Flow | C20: =C6-C17 -> -274983.33 | D20: =D6-D17 -> 32516.667 | E20: =E6-E17 -> 60016.667 | F20: =F6-F17 -> 152516.67 | G20: =G6-G17 -> 152516.67 | H20: =H6-H17 -> 152516.67
A21: Ending Cash | C21: =C19+C20 -> -274983.33 | D21: =D19+D20 -> -242466.67 | E21: =E19+E20 -> -182450 | F21: =F19+F20 -> -29933.333 | G21: =G19+G20 -> 122583.33 | H21: =H19+H20 -> 275100
A24: LOWER DEAL
C26: July | D26: August | E26: September | F26: October | G26: November | H26: December | I26: Totals
A27: CASH INFLOWS | M27: Average Daily Sales | O27: Age of A/R
A28: Sales | B28: 250,000/mo*.93 | D28: =M28*4.5 -> 34875 | E28: =$M$28*30 -> 232500 | F28: =$M$28*30 -> 232500 | G28: =$M$28*30 -> 232500 | H28: =$M$28*30 -> 232500 | I28: =SUM(C28:H28) -> 964875 | M28: =(250000*12*0.93)/360 -> 7750 | O28: 55.5 days
A30: Cash Outflows | M30: August will receive 4.5 days of sales (60 days-55.5 days)
A31: Operating Outflows:
A32: Salaries | B32: 40,000/year | C32: =40000/12 -> 3333.3333 | D32: =40000/12 -> 3333.3333 | E32: =40000/12 -> 3333.3333 | F32: =40000/12 -> 3333.3333 | G32: =40000/12 -> 3333.3333 | H32: =40000/12 -> 3333.3333 | I32: =SUM(C32:H32) -> 20000
A33: Car Allowance | B33: 10,200/year | C33: =10200/12 -> 850 | D33: =10200/12 -> 850 | E33: =10200/12 -> 850 | F33: =10200/12 -> 850 | G33: =10200/12 -> 850 | H33: =10200/12 -> 850 | I33: =SUM(C33:H33) -> 5100 | M33: Average Daily COGS | O33: Age of A/P
A34: Maintenance Costs | B34: 9,600/year | C34: =9600/12 -> 800 | D34: =9600/12 -> 800 | E34: =9600/12 -> 800 | F34: =9600/12 -> 800 | G34: =9600/12 -> 800 | H34: =9600/12 -> 800 | I34: =SUM(C34:H34) -> 4800 | M34: =(250000*12)*0.37/360 -> 3083.3333 | O34: 60 days
A35: COGS | E35: =$M$11*30 -> 92500 | F35: =$M$11*30 -> 92500 | G35: =$M$11*30 -> 92500 | H35: =$M$11*30 -> 92500 | I35: =SUM(C35:H35) -> 370000
A36: Investment Outflows: | M36: September will need to pay for 60 days of inventory
A37: Equipment | B37: Purchased by Cargill | I37: =SUM(C37:H37) -> 0 | M37: (month to keep in inventory and July's used inventory)
A38: Inventory | E38: =E35 -> 92500 | I38: =SUM(C38:H38) -> 92500
A39: Total Outflows | C39: =SUM(C32:C38) -> 4983.3333 | D39: =SUM(D32:D38) -> 4983.3333 | E39: =SUM(E32:E38) -> 189983.33 | F39: =SUM(F32:F38) -> 97483.333 | G39: =SUM(G32:G38) -> 97483.333 | H39: =SUM(H32:H38) -> 97483.333 | I39: =SUM(I32:I38) -> 492400
A41: Beginning Cash | C41: 0 | D41: =C43 -> -4983.3333 | E41: =D43 -> 24908.333 | F41: =E43 -> 67425 | G41: =F43 -> 202441.67 | H41: =G43 -> 337458.33
A42: Net Cash Flow | C42: =C28-C39 -> -4983.3333 | D42: =D28-D39 -> 29891.667 | E42: =E28-E39 -> 42516.667 | F42: =F28-F39 -> 135016.67 | G42: =G28-G39 -> 135016.67 | H42: =H28-H39 -> 135016.67
A43: Ending Cash | C43: =C41+C42 -> -4983.3333 | D43: =D41+D42 -> 24908.333 | E43: =E41+E42 -> 67425 | F43: =F41+F42 -> 202441.67 | G43: =G41+G42 -> 337458.33 | H43: =H41+H42 -> 472475

Sheet Differential
A1: ADEPT
C3: Original Deal | D3: Lower Deal
A4: Cash Inflows
A5: Sales | B5: Given/7% lower | C5: =250000*12 -> 3000000 | D5: =C5*0.93 -> 2790000
A7: Cash Outflows
A8: COGS | B8: 37% of Sales (100%-63%) | C8: =C5*0.37 -> 1110000 | D8: =C8 -> 1110000
A9: Salaries | B9: given | C9: =40000 -> 40000 | D9: =C9 -> 40000
A10: Car Allowance | B10: given | C10: =10200 -> 10200 | D10: =C10 -> 10200
A11: Maintenance Costs | B11: =B10 -> given | C11: =9600 -> 9600 | D11: =C11 -> 9600
A12: Total Outflows | C12: =SUM(C8:C11) -> 1169800 | D12: =SUM(D8:D11) -> 1169800
A14: Net Cash Flow | C14: =C5-C12 -> 1830200 | D14: =D5-D12 -> 1620200
A16: Investments
A17: Equipment | B17: 30,000*9 | C17: =30000*9 -> 270000 | D17: 0
A18: Inventory | B18: Cogs/360*30 | C18: =C8/360*30 -> 92500 | D18: =D8/360*30 -> 92500
A19: A/R | B19: 55.5 days (calculated) | C19: =C5/360*55.5 -> 462500 | D19: =D5/360*55.5 -> 430125 | XFD19: =XFD5/360*55.5 -> 0
A20: A/P | B20: 60 days | C20: =-(C8/360*60) -> -185000 | D20: =-(D8/360*60) -> -185000
A21: Total Investments | C21: =SUM(C17:C20) -> 640000 | D21: =SUM(D17:D20) -> 337625
A23: ROI | C23: =C14/C21 -> 2.8596875 | D23: =D14/D21 -> 4.7988153
A24: Payback | C24: =C21/C14 -> 0.34968856 | D24: =D21/D14 -> 0.20838477
A26: Breakeven | B26: Fixed Costs | C26: Salary | D26: 40000
C27: Car Allowance | D27: =850*12 -> 10200
B28: Total Fixed Costs | D28: =D26+D27 -> 50200
B30: Variable Costs as a Percentage | C30: Commission | D30: 0.25 | E30: ***It is important to use the COGS from the I/S, not the differential as the differential
C31: COGS | D31: 0.569 | E31: sales do not earn a commission, nor will the son have anything to do with the sale to Cargill
B32: Total Variable Costs as a Percentage | D32: =D30+D31 -> 0.819
B34: Contribution Margin Rate (CMR) | C34: Sales | D34: 1
B35: (Sales (As a %)-VC (As a %)) | C35: Variable Costs | D35: =D32 -> 0.819
D36: =D34-D35 -> 0.181
B38: Breakeven Sales | C38: Fixed Costs/CMR
C39: 50,200/18.1% | D39: =D28/D36 -> 277348.07

Sheet Proj. Income Statement
A1: ADEPT
C3: 2007 | D3: Original Deal | E3: Lower Deal
A4: REVENUE
A5: Existing Sales | B5: (859,679-634,715)/634,715=35% growth | C5: 859679 | D5: =C5*1.35/12 -> 96713.888 | E5: =D5 -> 96713.888
A6: Differential Sales | D6: =Differential!C5/12 -> 250000 | E6: =Differential!D5/12 -> 232500
A7: Total Revenue | C7: =SUM(C5:C6) -> 859679 | D7: =SUM(D5:D6) -> 346713.89 | E7: =SUM(E5:E6) -> 329213.89
A9: Existing COGS | B9: 57% of Existing Sales | C9: =C7*0.57 -> 490017.03 | D9: =D5*0.57 -> 55126.916 | E9: =E5*0.57 -> 55126.916
A10: Differential COGS | B10: 37% of Differention Sales At Original Price | C10: 0 | D10: =Differential!C8/12 -> 92500 | E10: =Differential!D8/12 -> 92500
A12: Gross Profit | C12: =C7-C9 -> 369661.97 | D12: =D7-D9-D10 -> 199086.97 | E12: =E7-E9-E10 -> 181586.97
A14: Total Operating Expenses | B14: 38% of Existing sales | C14: =C7*0.38 -> 326678.02 | D14: =D5*0.382 -> 36944.705 | E14: =E5*0.382 -> 36944.705
A15: Diff. Outflows (Exclude COGS) | D15: =(Differential!C9+Differential!C10+Differential!C11)/12 -> 4983.3333 | E15: =SUM(Differential!D9:D11) -> 59800
A16: Amortization | B16: 270,000/10/12 | D16: =270000/10/12 -> 2250 | E16: =270000/10/12 -> 2250
F17: ***Keep in mind the projections are only
A18: NET INCOME | C18: =C12-C14 -> 42983.95 | D18: =D12-D14-D15-D16 -> 154908.93 | E18: =E12-E14-E15-E16 -> 82592.267 | F18: for one month, where as 2007 is for an entire
F19: year. This new deal increases revenue SIGNIFICANTLY

Sheet Proj. Balance Sheet
A1: ADEPT
B3: Assumptions | C3: 2007 | D3: Original | E3: Lower
A4: ASSETS
A5: Current Assets
A6: Cash | B6: Same Dollar | C6: =C10-C9-C8-C7 -> 0 | D6: 0 | E6: 0
A7: Accounts Receivable | B7: A/R From 2007 + (Diff A/R*30/55.5) | C7: 132613 | D7: =C7+(Differential!C19*(30/55.5)) -> 382613 | E7: =C7+(Differential!D19*30/55.5) -> 365113
A8: Prepaids | B8: Same $ | C8: 4388 | D8: =C8 -> 4388 | E8: =C8 -> 4388
A9: Inventory | B9: Inv From 2007 + Diff Inv | C9: 19908 | D9: =C9+Differential!C18 -> 112408 | E9: =C9+Differential!D18 -> 112408
A10: Total Current Assets | C10: =C18-C16 -> 156909 | D10: =SUM(D6:D9) -> 499409 | E10: =SUM(E6:E9) -> 481909
A12: Capital Assets
A13: Old Capital Assets | B13: Less 10,990 (Yearly Dep'n)*1/12 | C13: 92948 | D13: =C13-(10990*1/12) -> 92032.167 | E13: =C13-(10990*1/12) -> 92032.167
A14: New Equipment | B14: Taken from Differential | D14: =Differential!C17 -> 270000 | E14: 0
A15: Accumulated Amortization | B15: 270,000/10*(1/12) | D15: =-D14/10*(1/12) -> -2250 | E15: 0
A16: Total Capital Assets | C16: =C13 -> 92948 | D16: =D13+D14+D15 -> 359782.17 | E16: =E13+E14+E15 -> 92032.167
A18: Total Assets | C18: =C41 -> 249857 | D18: =D10+D16 -> 859191.17 | E18: =E10+E16 -> 573941.17
A20: LIABILITIES & SHAREHOLDERS' EQUITY
A21: Current Liabilities
A22: Operating Line of Credit | B22: Same Dollar | C22: 34327 | D22: =C22 -> 34327 | E22: =D22 -> 34327
A23: Accounts Payable | B23: A/P From 2007 + (Diff A/P*30/60) | C23: 113250 | D23: =$C$23+(-Differential!C20*30/60) -> 205750 | E23: =$C$23+(-Differential!D20*30/60) -> 205750
A24: Accrued Liabilities & Other Current Payables | B24: Same Dollar | C24: 5575 | D24: =C24 -> 5575 | E24: =D24 -> 5575
A25: Additional Loan | B25: PLUG | D25: =D26-(SUM(D22:D24)) -> 361925.23 | E25: =E26-SUM(E22:E24) -> 148991.9 | F25: ***ADDITIONAL FINANCING REQUIRED
A26: Total Current Liabilities | C26: =SUM(C22:C24) -> 153152 | D26: =D34-D32 -> 607577.23 | E26: =E34-E32 -> 394643.9
A28: Long-Term Liabilities
A29: Sodrox Term Loan | B29: Same Dollar | C29: 88000 | D29: =C29 -> 88000 | E29: =C29 -> 88000
A30: Shareholder Loan | B30: Same Dollar | C30: 45000 | D30: =C30 -> 45000 | E30: =D30 -> 45000
A31: Personal Loan | B31: Same Dollar | C31: 42240 | D31: =C31 -> 42240 | E31: =D31 -> 42240
A32: Total Long-term Liabilities | C32: =SUM(C29:C31) -> 175240 | D32: =SUM(D29:D31) -> 175240 | E32: =SUM(E29:E31) -> 175240
A34: Total Liabilities | C34: =C26+C32 -> 328392 | D34: =D41-D39 -> 782817.23 | E34: =E41-E39 -> 569883.9
A36: Shareholders' Equity
A37: Capital Stock | B37: Same Dollar | C37: 120000 | D37: =C37 -> 120000 | E37: =D37 -> 120000
A38: Retained Earnings | B38: Last Year's R/E + Projected Net Income | C38: -198535 | D38: =C38+'Proj. Income Statement'!D18 -> -43626.067 | E38: =C38+'Proj. Income Statement'!E18 -> -115942.73
A39: Total Shareholders' Equity | C39: =C37+C38 -> -78535 | D39: =D37+D38 -> 76373.933 | E39: =E37+E38 -> 4057.2666
A41: Total Liabilities & Shareholders' Equity | C41: =C34+C39 -> 249857 | D41: =D18 -> 859191.17 | E41: =E18 -> 573941.17
