Workbook

Sheet  3.5
B2: Low (7) | F2: High (15)
A3: Investments | E3: Investments
A4: Equipment | C4: 1385845 | E4: Equipment | G4: 1385845
A5: Trucks | C5: 1396721 | E5: Trucks | G5: 1396721
A6: Training | B6: 35000 / 12 | C6: =35000/12 -> 2916.6667 | E6: Training | F6: 35000 / 12 | G6: =35000/12 -> 2916.6667
A7: Training | B7: 90 000/12 *3.5 | C7: =90000/12*3.5 -> 26250 | E7: Training | F7: 90 000/12 *7.5 | G7: =90000/12*7.5 -> 56250
A8: Working Capital AR | B8: 30 days of revenue | C8: =C14/365 *30 -> 201369.86 | E8: Working Capital AR | F8: 30 Days of Revenue | G8: =G14/365 *30 -> 431506.85
A9: Total | C9: =SUM(C4:C8) -> 3013102.5 | E9: Total | G9: =SUM(G4:G8) -> 3273239.5
A11: Inflow | E11: Inflow
A12: Contracts | B12: 7 | E12: Contracts | F12: 15
A13: Revenue per contract | B13: 350000 | E13: Revenue per contract | F13: 350000
A14: Revenue (Additional) | C14: =B12*B13 -> 2450000 | E14: Revenue (Additional) | G14: =F12*F13 -> 5250000
A15: Top Soils Savings | B15: 10% of Top Soil sales 0.1*0.15* 7 263 015 | C15: =0.15*0.1*7263015 -> 108945.22 | E15: Top Soils Savings | F15: 10% of Top Soil sales 0.1*0.15* 7 263 015 | G15: =0.15*0.1*7263015 -> 108945.22
A16: Subcontracting Savings | B16: 700 000 | C16: 700000 | E16: Subcontracting Savings | F16: 700 000 | G16: 700000
A17: Total | C17: =SUM(C14:C16) -> 3258945.2 | E17: Total | G17: =SUM(G14:G16) -> 6058945.2
A19: Outflow | E19: Outflow
A20: Construction Expenses | B20: 0.25 | C20: =C14*B20 -> 612500 | E20: Construction Expenses | F20: 0.25 | G20: =G14*F20 -> 1312500
A21: Employee (operators) | B21: 4*10h*6days*30$*7*16 | C21: =4*10*6*30*16*7 -> 806400 | E21: Employee (operators) | F21: 4*10h*6days*30$*15*16 | G21: =4*10*6*30*16*15 -> 1728000
A22: Employee (supervisor) | B22: 90 000 * 3.5 | C22: =90000*3.5 -> 315000 | E22: Employee (supervisor) | F22: 90 000 * 7.5 | G22: =90000*7.5 -> 675000
A23: Employee(Admin) | B23: 35 000 | C23: 35000 | E23: Employee(Admin) | F23: 35 000 | G23: 35000
A24: Total | C24: =SUM(C20:C23) -> 1768900 | E24: Total | G24: =SUM(G20:G23) -> 3750500
A26: Net gain | C26: =C17-C24 -> 1490045.2 | E26: Net Gain | G26: =G17-G24 -> 2308445.2
A28: ROI | C28: =C26/C9 -> 0.49452191 | E28: ROI | G28: =G26/G9 -> 0.70524788
A29: PayBack | B29: Years | C29: =C9/C26 -> 2.0221551 | E29: PayBack | F29: Years | G29: =G9/G26 -> 1.4179412

Sheet Differential 
B2: Low (7) | F2: High (15)
A3: Investments | E3: Investments
A4: Equipment | C4: 1385845 | E4: Equipment | G4: 1385845
A5: Trucks | C5: 1396721 | E5: Trucks | G5: 1396721
A6: Training | B6: 35000 / 12 | C6: =35000/12 -> 2916.6667 | E6: Training | F6: 35000 / 12 | G6: =35000/12 -> 2916.6667
A7: Training | B7: 90 000/12 *4 | C7: =90000/12*4 -> 30000 | E7: Training | F7: 90 000/12 *8 | G7: =90000/12*8 -> 60000
A8: Working Capital AR | B8: 30 days of revenue | C8: =C15/360 *30 -> 204166.67 | E8: Working Capital AR | F8: 30 Days of Revenue | G8: =G15/360 *30 -> 437500
A9: AP | B9: 700000 less (62.5 days worth) ap | C9: =700000/360*62.5 -> 121527.78 | E9: AP | F9: 700000 less (62.5 days worth) ap | G9: =700000/360*62.5 -> 121527.78
A10: Total | C10: =SUM(C4:C9) -> 3141177.1 | E10: Total | G10: =SUM(G4:G9) -> 3404510.4
A12: Inflow | E12: Inflow
A13: Contracts | B13: 7 | E13: Contracts | F13: 15
A14: Revenue per contract | B14: 350000 | E14: Revenue per contract | F14: 350000
A15: Revenue (Additional) | C15: =B13*B14 -> 2450000 | E15: Revenue (Additional) | G15: =F13*F14 -> 5250000
A16: Top Soils Savings | B16: 10% of Top Soil sales 0.1*0.15* 2012 revenue *105% | C16: =0.15*0.1*1.05*7263015 -> 114392.49 | E16: Top Soils Savings | F16: 10% of Top Soil sales 0.1*0.15* 7408275.3 | G16: =0.15*0.1*105%*7263015 -> 114392.49
A17: Subcontracting Savings | B17: 700 000 | C17: 700000 | E17: Subcontracting Savings | F17: 700 000 | G17: 700000
A18: Total | C18: =SUM(C15:C17) -> 3264392.5 | E18: Total | G18: =SUM(G15:G17) -> 6064392.5
A20: Outflow | E20: Outflow
A21: Construction Expenses | B21: 0.25 | C21: =C15*B21 -> 612500 | E21: Construction Expenses | F21: 0.25 | G21: =G15*F21 -> 1312500
A22: Employee (operators) | B22: 4*10h*6days*30$*7*16 | C22: =4*10*6*30*16*7 -> 806400 | E22: Employee (operators) | F22: 4*10h*6days*30$*15*16 | G22: =4*10*6*30*16*15 -> 1728000
A23: Employee (supervisor) | B23: 90 000 * 4 | C23: =90000*4 -> 360000 | E23: Employee (supervisor) | F23: 90 000 * 8 | G23: =90000*8 -> 720000
A24: Employee(Admin) | B24: 35 000 | C24: 35000 | E24: Employee(Admin) | F24: 35 000 | G24: 35000
A25: Total | C25: =SUM(C21:C24) -> 1813900 | E25: Total | G25: =SUM(G21:G24) -> 3795500
A27: Net gain | C27: =C18-C25 -> 1450492.5 | E27: Net Gain | G27: =G18-G25 -> 2268892.5
A29: ROI | C29: =C27/C10 -> 0.46176718 | E29: ROI | G29: =G27/G10 -> 0.66643722
A30: PayBack | B30: Years | C30: =C10/C27 -> 2.1655935 | E30: PayBack | F30: Years | G30: =G10/G27 -> 1.5005164

Sheet Income Statement + BS
B1: Income Statement (Status Quo) | H1: Income Statement (Expand Low) | O1: Balance Sheet (Expand Low)
A2: Revenue | G2: Revenue | N2: Assets
A3: Sales | B3: 2% increase on 7263015*85% | D3: =7263015*0.85*1.02 -> 6297034 | G3: Sales | H3: 2% increase on 7263015*85% | J3: =7263015*0.85*1.02 -> 6297034 | N3: Current Assets
A4: Top Soil | B4: 5% increase on 7263015*15% | D4: =7263015*0.15*1.05 -> 1143924.9 | G4: Top Soil | H4: 5% increase on 7263015*15% | J4: =7263015*0.15*1.05 -> 1143924.9 | N4: Cash | O4: Wanted | P4: 50000
G5: Sales Original Biz | J5: =J3+J4 -> 7440958.9 | L5: 7440958.9 | N5: AR ( old biz) | O5: 68.5 days | P5: =J5/360*68.5 -> 1415849.1
A6: Total Sales | D6: =SUM(D3:D5) -> 7440958.9 | E6: 1 | G6: Excavating Sales | J6: ='Differential '!C15 -> 2450000 | N6: AR (excavating) | O6: 30 days | P6: ='Differential '!C8 -> 204166.67
A7: Expenses | G7: Total Sales | J7: =J6+J5 -> 9890958.9 | K7: 1 | N7: Total Current Assets | P7: =SUM(P4:P6) -> 1670015.8
A8: Truck Expense | C8: =$D$6*E8 -> 2031381.8 | E8: 0.273 | G8: Expenses
A9: Truck Expense New | C9: 0 | G9: Truck Expense | I9: =$J$5*K9 -> 2031381.8 | K9: 0.273 | N9: Fixed Assets
A10: Total Truck Expense | D10: =C8+C9 -> 2031381.8 | G10: Truck Expense New | I10: ='Differential '!C21 -> 612500 | N10: Trucks | P10: 6955434
A11: Sub Contracts | D11: =$D$6*E11 -> 1867680.7 | E11: 0.251 | G11: Total Truck Expense | J11: =I9+I10 -> 2643881.8 | N11: New stuff | P11: 2782566
A12: Salaries | C12: =$D$6*E12 -> 1391459.3 | E12: 0.187 | G12: Sub Contracts | J12: =$J$5*K12 - 700000 -> 1167680.7 | K12: 0.251 | N12: Furniture | P12: 160715
A13: Salaries (New) | C13: 0 | G13: Salaries | I13: =$J$5*K13 -> 1391459.3 | K13: 0.187 | N13: Less: Acc Dep | P13: =(4922770+J31)*-1 -> -5925744.6
A14: Total Salaries | D14: =C12+C13 -> 1391459.3 | G14: Salaries (New) | I14: ='Differential '!C23+'Differential '!C24 -> 395000 | N14: Total Capital Assets | P14: =SUM(P10:P13) -> 3972970.4
A15: Purchases | D15: =$D$6*E15 -> 580394.79 | E15: 0.078 | G15: Total Salaries | J15: =I13+I14 -> 1786459.3 | N15: Total Assets | P15: =P14+P7 -> 5642986.2
A16: Management Wages | D16: =$D$6*E16 -> 111614.38 | E16: 0.015 | G16: Operator Wages | J16: ='Differential '!C22 -> 806400
A17: Office General | D17: =$D$6*E17 -> 81850.548 | E17: 0.011 | G17: Top Soil Savings | J17: =-1*'Differential '!C16 -> -114392.49 | N17: Liabilities and Shareholders Equity
A18: Int and bank | D18: =$D$6*E18 -> 59527.671 | E18: 0.008 | G18: Purchases | J18: =$J$5*K18 -> 580394.79 | K18: 0.078 | N18: Current Liabilities
A19: Professional Fees | D19: =$D$6*E19 -> 29763.835 | E19: 0.004 | G19: Management Wages | J19: =$J$5*K19 -> 111614.38 | K19: 0.015 | N19: Bank loan | O19: Plugged | P19: 903990
A20: Ad promo | D20: =$D$6*E20 -> 29763.835 | E20: 0.004 | G20: Office General | J20: =$J$5*K20 -> 81850.548 | K20: 0.011 | N20: Income Taxes Payable | P20: ='Income Statement + BS'!J35 -> 249041.41
A21: Telephone | D21: =$D$6*E21 -> 22322.877 | E21: 0.003 | G21: Int and bank | J21: =$J$5*K21 -> 59527.671 | K21: 0.008 | N21: Accounts Payable | O21: 62.5 | P21: =O21/360*J12 -> 202722.34
A22: Rent | D22: 15000 | E22: same $ | G22: Professional Fees | J22: =$J$5*K22 -> 29763.835 | K22: 0.004 | N22: AP reduction
A23: Meals Entertainment | D23: =$D$6*E23 -> 7440.9589 | E23: 0.001 | G23: Ad promo | J23: =$J$5*K23 -> 29763.835 | K23: 0.004
A24: Bad Debt Exp | B24: 0 | D24: 0 | E24: 0 | G24: Telephone | J24: =$J$5*K24 -> 22322.877 | K24: 0.003 | N24: Current Portion Loan | P24: 507012
A25: Gain on trucks | B25: 0 | D25: 0 | E25: 0 | G25: Rent | J25: 15000 | K25: same $ | N25: Shareholder loan | P25: 0
A26: Depreciation | B26: old | C26: 724718 | E26: =C26/D6 -> 0.097395781 | G26: Meals Entertainment | J26: =$J$5*K26 -> 7440.9589 | K26: 0.001 | N26: Total Current Liabilities | P26: =SUM(P19:P25) -> 1862765.8
A27: Depreciation | B27: New | C27: 0 | E27: =C27/D6 -> 0 | G27: Bad Debt Exp | H27: 0 | J27: 0 | K27: 0
A28: Total Depreciation | D28: =C26+C27 -> 724718 | G28: Gain on trucks | H28: 0 | J28: 0 | K28: 0 | N28: Long Term Loan | O28: moved to current | P28: 0
A29: Total Expenses | D29: =SUM(D8:D28) -> 6952918.7 | E29: =SUM(E8:E27) -> 0.93239578 | G29: Depreciation | H29: old | I29: 724718 | K29: =I29/J7 -> 0.073270753
G30: Depreciation | H30: New | I30: =('Differential '!C4+'Differential '!C5)/10 -> 278256.6 | K30: =I30/J7 -> 0.028132419 | N30: Total Liabilities | P30: =SUM(P26,P28) -> 1862765.8
A31: Net Income b4 tax | D31: =D6-D29 -> 488040.21 | E31: =D31/D6 -> 0.06558835 | G31: Total Depreciation | J31: =I29+I30 -> 1002974.6
A32: Income Tx | D32: =IF(D31>0,D31*E32,0) -> 73206.032 | E32: 0.15 | G32: Total Expenses | J32: =SUM(J9:J31) -> 8230682.8 | K32: =SUM(K9:K30) -> 0.93640317 | N32: Shareholders Equity
A33: Net Income after Tax | D33: =D31-D32 -> 414834.18 | E33: =D33/D6 -> 0.055750097 | N33: Common Stock | P33: 100
G34: Net Income b4 tax | J34: =J7-J32 -> 1660276.1 | K34: =J34/J7 -> 0.16785795 | N34: Retined Earnings | O34: old + projected | P34: =2368886+J36 -> 3780120.7
G35: Income Tx | J35: =IF(J34>0,J34*K35,0) -> 249041.41 | K35: 0.15 | N35: Total shareholders Equity | P35: =SUM(P33:P34) -> 3780220.7
G36: Net Income after Tax | J36: =J34-J35 -> 1411234.7 | K36: =J36/J7 -> 0.14267926 | N36: Total Liability and Shareholders Equity | P36: =P35+P30 -> 5642986.4
N39: Days of AP
N40: =316386/1822497*360 -> 62.496103
I43: =I14+I10+J16-700000+J17 -> 999507.51
