Workbook

Sheet Investments
B2: Rosa's Palas Franchise
B4: Initial Investment Required
B6: Franchise Fee | C6: 50000
B7: Liquor License | C7: =1000 -> 1000
B8: Inventory | C8: 15000
B9: Cash Float | C9: 20000
B10: Fixed Assets | C10: 390000
B11: Total | C11: =SUM(C6:C10) -> 476000
B13: Equity Infusion | C13: 50000
B14: Bank Loan | C14: =C11-C13 -> 426000
B15: Total | C15: =SUM(C13:C14) -> 476000

Sheet VC
B2: Rosa's Palas Franchise
B4: Variable Cost Schedule
B6: Food Costs | C6: 0.35 | E6: *Ansari's Predictions NOT Waller's
B7: Payroll Costs | C7: 0.2 | E7: *Ansari's Predictions NOT Waller's
B8: Payroll Taxes | C8: =C7*10% -> 0.02
B9: Royalty | C9: 0.04
B10: Paper Goods | C10: 0.015
B11: Laundry and Maintenance | C11: 0.006
B12: Cash Short | C12: 0.005
B13: Credit Card | C13: 0.021
B14: Total | C14: =SUM(C6:C13) -> 0.657
B16: Contribution Margin | C16: =100%-C14 -> 0.343

Sheet FC
B2: Rosa's Palas Franchise
B4: Fixed Cost Schedule
C6: Year 1 | D6: Year 2 | E6: Year 3
B7: EXPENSES
B8: Cash Expenses (evenly distributed through each year)
B9: Advertising | C9: 75000 | D9: 75000 | E9: 75000
B10: Rent | C10: =20*3500 -> 70000 | D10: =20*3500 -> 70000 | E10: =20*3500 -> 70000
B11: Legal | C11: =300*12 -> 3600 | D11: =300*12 -> 3600 | E11: =300*12 -> 3600 | H11: Sales above 1,600,000 | J11: used for calculattion of bonuses
B12: Manager's Salary | C12: 40000 | D12: 40000 | E12: 40000 | H12: Year 1 | I12: =IF(IS!$C$12>1600000,1.5%*IS!$C$12-1600000,0) -> 0
B13: Total Cash Expenses | C13: =SUM(C9:C12) -> 188600 | D13: =SUM(D9:D12) -> 188600 | E13: =SUM(E9:E12) -> 188600 | H13: Year 2 | I13: =IF(IS!D12>1600000,IS!D12-1600000,0) -> 0
H14: Year 3 | I14: =IF(IS!E12>1600000,IS!E12-1600000,0) -> 0
B15: Accounts Payable Expenses (1 month delayed payment)
B16: Utilities | C16: =70%*42000 -> 29400 | D16: =C16+2000 -> 31400 | E16: =D16+2000 -> 33400
B17: Repairs | C17: 14000 | D17: 14000 | E17: 14000
B18: Insurance | C18: 12000 | D18: 12000 | E18: 12000
B19: Phone | C19: 10000 | D19: 10000 | E19: 10000
B20: Total Accounts Payable Expenses | C20: =SUM(C16:C19) -> 65400 | D20: =SUM(D16:D19) -> 67400 | E20: =SUM(E16:E19) -> 69400
B22: Single Payment Expenses
B23: Liquor License | C23: =1200 -> 1200 | D23: 1200 | E23: 1200 | I23: *One time payment, last several years (1000 NOT an expense)
B24: Bonus | C24: =IF(IS!C12>1600000,1.5%*(IS!C12-1600000),0) -> 0 | D24: =IF(IS!D12>1600000,1.5%*(IS!D12-1600000),0) -> 0 | E24: =IF(IS!E12>1600000,1.5%*(IS!E12-1600000),0) -> 0
B25: Total Single Payment Expenses | C25: =SUM(C23:C24) -> 1200 | D25: =SUM(D23:D24) -> 1200 | E25: =SUM(E23:E24) -> 1200
B27: Non-Cash Expenses
B28: Depreciation - Fixed Assets | C28: 139286 | D28: 71633 | E28: 59694
B29: Amortization - Franchise Fee | C29: =(Investments!$C$6/5) -> 10000 | D29: =(Investments!$C$6/5) -> 10000 | E29: =(Investments!$C$6/5) -> 10000 | I29: * Don’t amortize stuff u pay recurring, those don’t provide future economic benefits and will be expensed yearly
B30: Amortization - Liquor License | C30: =Investments!$C$7/5 -> 200 | D30: =Investments!$C$7/5 -> 200 | E30: =Investments!$C$7/5 -> 200
B31: Total Non-Cash Expenses | C31: =SUM(C28:C30) -> 149486 | D31: =SUM(D28:D30) -> 81833 | E31: =SUM(E28:E30) -> 69894
B33: Total Non-Interest Fixed Costs | C33: =SUM(C20,C25,C31,C13) -> 404686 | D33: =SUM(D20,D25,D31,D13) -> 339033 | E33: =SUM(E20,E25,E31,E13) -> 329094
B35: INTEREST
B36: Interest | C36: =Investments!$C$14*8% -> 34080 | D36: =BS!D21*8% -> 21919.2 | E36: =BS!F21*8% -> 5847.7867
B38: Total Fixed Costs | C38: =SUM(C33,C36) -> 438766 | D38: =SUM(D33,D36) -> 360952.2 | E38: =SUM(E33,E36) -> 334941.79

Sheet IS
B2: Rosa's Palas Franchise
B4: Three-Year Income Statement Projections
C6: Year 1 | D6: Year 2 | E6: Year 3
B7: Waller's Estimate | C7: =1600000 -> 1600000 | D7: =C7+150000 -> 1750000 | E7: =D7+150000 -> 1900000
B8: Sales Estimate Adjustment (%) | C8: 0.8 | D8: 0.8 | E8: 0.8
B9: Sales Estimate | C9: =C8*C7 -> 1280000 | D9: =D8*D7 -> 1400000 | E9: =E8*E7 -> 1520000
C11: Year 1 | D11: Year 2 | E11: Year 3
B12: Sales | C12: =C9 -> 1280000 | D12: =D9 -> 1400000 | E12: =E9 -> 1520000
B13: Less: Variable Costs | C13: =C12*(VC!$C$14) -> 840960 | D13: =D12*(VC!$C$14) -> 919800 | E13: =E12*(VC!$C$14) -> 998640
B14: Contribution | C14: =C12-C13 -> 439040 | D14: =D12-D13 -> 480200 | E14: =E12-E13 -> 521360
B16: Fixed Costs | C16: =FC!C33 -> 404686 | D16: =FC!D33 -> 339033 | E16: =FC!E33 -> 329094
B18: Earnings Before Interest and Tax | C18: =C14-C16 -> 34354 | D18: =D14-D16 -> 141167 | E18: =E14-E16 -> 192266
B19: Less: Interest | C19: =FC!C36 -> 34080 | D19: =FC!D36 -> 21919.2 | E19: =FC!E36 -> 5847.7867
B20: Net Income Before Tax | C20: =C18-C19 -> 274 | D20: =D18-D19 -> 119247.8 | E20: =E18-E19 -> 186418.21
B21: Less: Tax | C21: =IF(C20<0,0,IF(C20<50000,C20*0.2,IF(50000<C20<100000,50000*20%+(C20-50000)*22%,50000*20%+50000*22%+(C20-100000)*48%))) -> 54.8 | D21: =IF(D20<0,0,IF(D20<50000,D20*0.2,IF(50000<D20<100000,50000*20%+(D20-50000)*22%,50000*20%+50000*22%+(D20-100000)*48%))) -> 30238.944 | E21: =IF(E20<0,0,IF(E20<50000,E20*0.2,IF(50000<E20<100000,50000*20%+(E20-50000)*22%,50000*20%+50000*22%+(E20-100000)*48%))) -> 62480.742
B22: Net Income | C22: =C20-C21 -> 219.2 | D22: =D20-D21 -> 89008.856 | E22: =E20-E21 -> 123937.47
B26: If NOT GIVEN COST SCHEDULES MUST BREAK OUT
B27: ALL THE COSTS, (i.e. rent, phone salaries, etc)

Sheet CB Yr.1
B2: Rosa's Palas Franchise
B4: ANNUAL CASH BUDGET
B6: Year 1
C8: March | D8: April | E8: May | F8: June | G8: July | H8: August | I8: September | J8: October | K8: November | L8: December | M8: January | N8: February | O8: Totals
B9: Sales | C9: =IS!$C$12/12 -> 106666.67 | D9: =IS!$C$12/12 -> 106666.67 | E9: =IS!$C$12/12 -> 106666.67 | F9: =IS!$C$12/12 -> 106666.67 | G9: =IS!$C$12/12 -> 106666.67 | H9: =IS!$C$12/12 -> 106666.67 | I9: =IS!$C$12/12 -> 106666.67 | J9: =IS!$C$12/12 -> 106666.67 | ... N9: =IS!$C$12/12 -> 106666.67 | O9: =SUM(C9:N9) -> 1280000
B11: Inflows:
B12: Collections | C12: =C9-(C9*60%*5%) -> 103466.67 | D12: =D9-(D9*60%*5%) -> 103466.67 | E12: =E9-(E9*60%*5%) -> 103466.67 | F12: =F9-(F9*60%*5%) -> 103466.67 | G12: =G9-(G9*60%*5%) -> 103466.67 | H12: =H9-(H9*60%*5%) -> 103466.67 | I12: =I9-(I9*60%*5%) -> 103466.67 | J12: =J9-(J9*60%*5%) -> 103466.67 | ... N12: =N9-(N9*60%*5%) -> 103466.67 | O12: =SUM(C12:N12) -> 1241600
B13: Non-Bank Credit Cards | C13: 0 | D13: =(C9*60%)*5% -> 3200 | E13: =(D9*60%)*5% -> 3200 | F13: =(E9*60%)*5% -> 3200 | G13: =(F9*60%)*5% -> 3200 | H13: =(G9*60%)*5% -> 3200 | I13: =(H9*60%)*5% -> 3200 | J13: =(I9*60%)*5% -> 3200 | K13: =(J9*60%)*5% -> 3200 | ... N13: =(M9*60%)*5% -> 3200 | O13: =SUM(C13:N13) -> 35200
B14: Equity Infusion | C14: =Investments!$C$6 -> 50000 | D14: 0 | E14: 0 | F14: 0 | G14: 0 | H14: 0 | I14: 0 | J14: 0 | K14: 0 | L14: 0 | M14: 0 | N14: 0 | O14: =SUM(C14:N14) -> 50000
B15: Bank Loan | C15: =Investments!$C$14 -> 426000 | D15: 0 | E15: 0 | F15: 0 | G15: 0 | H15: 0 | I15: 0 | J15: 0 | K15: 0 | L15: 0 | M15: 0 | N15: 0 | O15: =SUM(C15:N15) -> 426000
B16: Total Inflows | C16: =SUM(C12:C15) -> 579466.67 | D16: =SUM(D12:D15) -> 106666.67 | E16: =SUM(E12:E15) -> 106666.67 | F16: =SUM(F12:F15) -> 106666.67 | G16: =SUM(G12:G15) -> 106666.67 | H16: =SUM(H12:H15) -> 106666.67 | I16: =SUM(I12:I15) -> 106666.67 | J16: =SUM(J12:J15) -> 106666.67 | ... O16: =SUM(O12:O15) -> 1752800
B18: Outflows:
B19: Expenses
B20: Variable Costs | C20: =VC!$C$14*'CB Yr.1'!C9 -> 70080 | D20: =VC!$C$14*'CB Yr.1'!D9 -> 70080 | E20: =VC!$C$14*'CB Yr.1'!E9 -> 70080 | F20: =VC!$C$14*'CB Yr.1'!F9 -> 70080 | G20: =VC!$C$14*'CB Yr.1'!G9 -> 70080 | H20: =VC!$C$14*'CB Yr.1'!H9 -> 70080 | I20: =VC!$C$14*'CB Yr.1'!I9 -> 70080 | J20: =VC!$C$14*'CB Yr.1'!J9 -> 70080 | ... N20: =VC!$C$14*'CB Yr.1'!N9 -> 70080 | O20: =SUM(C20:N20) -> 840960
B21: Cash Expenses | C21: =(FC!$C$13)/12 -> 15716.667 | D21: =(FC!$C$13)/12 -> 15716.667 | E21: =(FC!$C$13)/12 -> 15716.667 | F21: =(FC!$C$13)/12 -> 15716.667 | G21: =(FC!$C$13)/12 -> 15716.667 | H21: =(FC!$C$13)/12 -> 15716.667 | I21: =(FC!$C$13)/12 -> 15716.667 | J21: =(FC!$C$13)/12 -> 15716.667 | ... N21: =(FC!$C$13)/12 -> 15716.667 | O21: =SUM(C21:N21) -> 188600
B22: Interest | C22: =IS!$C$19/12 -> 2840 | D22: =IS!$C$19/12 -> 2840 | E22: =IS!$C$19/12 -> 2840 | F22: =IS!$C$19/12 -> 2840 | G22: =IS!$C$19/12 -> 2840 | H22: =IS!$C$19/12 -> 2840 | I22: =IS!$C$19/12 -> 2840 | J22: =IS!$C$19/12 -> 2840 | ... N22: =IS!$C$19/12 -> 2840 | O22: =SUM(C22:N22) -> 34080
B23: A/P Expenses | C23: 0 | D23: =FC!$C$20/12 -> 5450 | E23: =FC!$C$20/12 -> 5450 | F23: =FC!$C$20/12 -> 5450 | G23: =FC!$C$20/12 -> 5450 | H23: =FC!$C$20/12 -> 5450 | I23: =FC!$C$20/12 -> 5450 | J23: =FC!$C$20/12 -> 5450 | K23: =FC!$C$20/12 -> 5450 | ... N23: =FC!$C$20/12 -> 5450 | O23: =SUM(C23:N23) -> 59950 | Q23: Note 5450 showing up in year 2
B24: Liquor License | C24: 1200 | D24: 0 | E24: 0 | F24: 0 | G24: 0 | H24: 0 | I24: 0 | J24: 0 | K24: 0 | L24: 0 | M24: 0 | N24: 0 | O24: =SUM(C24:N24) -> 1200 | Q24: BONUS PAIDS IN YEAR 2 (month and a half later - april IF PAID)
B25: Bonus | C25: 0 | D25: 0 | E25: 0 | F25: 0 | G25: 0 | H25: 0 | I25: 0 | J25: 0 | K25: 0 | L25: 0 | M25: 0 | N25: 0 | O25: =SUM(C25:N25) -> 0
B26: Tax | C26: 0 | D26: 0 | E26: 0 | F26: 0 | G26: 0 | H26: 0 | I26: 0 | J26: 0 | K26: 0 | L26: 0 | M26: 0 | N26: 0 | O26: =SUM(C26:N26) -> 0 | Q26: TAX PAID NEXT FY APRIL
B28: Investments
B29: Franchise Fee | C29: =Investments!C6 -> 50000 | O29: =SUM(C29:N29) -> 50000
B30: Liquor License | C30: =Investments!C7 -> 1000 | O30: =SUM(C30:N30) -> 1000
B31: Inventory | C31: =Investments!$C$8 -> 15000 | D31: 0 | E31: 0 | F31: 0 | G31: 0 | H31: 0 | I31: 0 | J31: 0 | K31: 0 | L31: 0 | M31: 0 | N31: 0 | O31: =SUM(C31:N31) -> 15000
B32: Fixed Assets | C32: =Investments!$C$10 -> 390000 | D32: 0 | E32: 0 | F32: 0 | G32: 0 | H32: 0 | I32: 0 | J32: 0 | K32: 0 | L32: 0 | M32: 0 | N32: 0 | O32: =SUM(C32:N32) -> 390000
B33: Loan Repayment | C33: 0 | D33: 0 | E33: 0 | F33: 0 | G33: 0 | H33: 0 | I33: 0 | J33: 0 | K33: 0 | L33: 0 | M33: 0 | N33: 152010 | O33: =SUM(C33:N33) -> 152010
B34: Total Outflows | C34: =SUM(C20:C33) -> 545836.67 | D34: =SUM(D20:D33) -> 94086.667 | E34: =SUM(E20:E33) -> 94086.667 | F34: =SUM(F20:F33) -> 94086.667 | G34: =SUM(G20:G33) -> 94086.667 | H34: =SUM(H20:H33) -> 94086.667 | I34: =SUM(I20:I33) -> 94086.667 | J34: =SUM(J20:J33) -> 94086.667 | ... O34: =SUM(O20:O33) -> 1732800
B35: Net Cash Flow | C35: =C16-C34 -> 33630 | D35: =D16-D34 -> 12580 | E35: =E16-E34 -> 12580 | F35: =F16-F34 -> 12580 | G35: =G16-G34 -> 12580 | H35: =H16-H34 -> 12580 | I35: =I16-I34 -> 12580 | J35: =J16-J34 -> 12580 | ... O35: =O16-O34 -> 20000
B36: Beginning Cash | C36: 0 | D36: =C37 -> 33630 | E36: =D37 -> 46210 | F36: =E37 -> 58790 | G36: =F37 -> 71370 | H36: =G37 -> 83950 | I36: =H37 -> 96530 | J36: =I37 -> 109110 | K36: =J37 -> 121690 | ... N36: =M37 -> 159430 | O36: 0
B37: Ending Cash | C37: =SUM(C35:C36) -> 33630 | D37: =SUM(D35:D36) -> 46210 | E37: =SUM(E35:E36) -> 58790 | F37: =SUM(F35:F36) -> 71370 | G37: =SUM(G35:G36) -> 83950 | H37: =SUM(H35:H36) -> 96530 | I37: =SUM(I35:I36) -> 109110 | J37: =SUM(J35:J36) -> 121690 | ... O37: =SUM(O35:O36) -> 20000
B39: ON feas, not likely get equal payments (MUST NOT be equal sales and account for recievables) | N39: If have any cash left, use it to pay back the loan!
N40: CASH IS KING, HUGE DIFFERENCE BETWEEN CASH AND PROFIT!
G41: GOAL SEEK! | N41: KEY INTEREST AND BANK LOAN STARTING YEARS 1 AND 2!
G42: uNDER DATA, what if analysis, will solve the answer!
G43: Great for things
G44: Doesn’t automatically update

Sheet CB Yr. 2
B2: Rosa's Palas Franchise
B4: ANNUAL CASH BUDGET
B6: Year 2
C8: March | D8: April | E8: May | F8: June | G8: July | H8: August | I8: September | J8: October | K8: November | L8: December | M8: January | N8: February | O8: Totals
B9: Sales | C9: =IS!$D$12/12 -> 116666.67 | D9: =IS!$D$12/12 -> 116666.67 | E9: =IS!$D$12/12 -> 116666.67 | F9: =IS!$D$12/12 -> 116666.67 | G9: =IS!$D$12/12 -> 116666.67 | H9: =IS!$D$12/12 -> 116666.67 | I9: =IS!$D$12/12 -> 116666.67 | J9: =IS!$D$12/12 -> 116666.67 | ... N9: =IS!$D$12/12 -> 116666.67 | O9: =SUM(C9:N9) -> 1400000
B11: Inflows:
B12: Collections | C12: =C9-(C9*60%*5%) -> 113166.67 | D12: =D9-(D9*60%*5%) -> 113166.67 | E12: =E9-(E9*60%*5%) -> 113166.67 | F12: =F9-(F9*60%*5%) -> 113166.67 | G12: =G9-(G9*60%*5%) -> 113166.67 | H12: =H9-(H9*60%*5%) -> 113166.67 | I12: =I9-(I9*60%*5%) -> 113166.67 | J12: =J9-(J9*60%*5%) -> 113166.67 | ... N12: =N9-(N9*60%*5%) -> 113166.67 | O12: =SUM(C12:N12) -> 1358000
B13: Non-Bank Credit Cards | C13: ='CB Yr.1'!N9*60%*5% -> 3200 | D13: =C9*60%*5% -> 3500 | E13: =D9*60%*5% -> 3500 | F13: =E9*60%*5% -> 3500 | G13: =F9*60%*5% -> 3500 | H13: =G9*60%*5% -> 3500 | I13: =H9*60%*5% -> 3500 | J13: =I9*60%*5% -> 3500 | K13: =J9*60%*5% -> 3500 | ... N13: =M9*60%*5% -> 3500 | O13: =SUM(C13:N13) -> 41700
B14: Total Inflows | C14: =SUM(C12,C13) -> 116366.67 | D14: =SUM(D12,D13) -> 116666.67 | E14: =SUM(E12,E13) -> 116666.67 | F14: =SUM(F12,F13) -> 116666.67 | G14: =SUM(G12,G13) -> 116666.67 | H14: =SUM(H12,H13) -> 116666.67 | I14: =SUM(I12,I13) -> 116666.67 | J14: =SUM(J12,J13) -> 116666.67 | ... N14: =SUM(N12,N13) -> 116666.67 | O14: =SUM(O12:O13) -> 1399700
B16: Outflows:
B17: Expenses
B18: Variable Costs | C18: =VC!$C$14*'CB Yr. 2'!C9 -> 76650 | D18: =VC!$C$14*'CB Yr. 2'!D9 -> 76650 | E18: =VC!$C$14*'CB Yr. 2'!E9 -> 76650 | F18: =VC!$C$14*'CB Yr. 2'!F9 -> 76650 | G18: =VC!$C$14*'CB Yr. 2'!G9 -> 76650 | H18: =VC!$C$14*'CB Yr. 2'!H9 -> 76650 | I18: =VC!$C$14*'CB Yr. 2'!I9 -> 76650 | J18: =VC!$C$14*'CB Yr. 2'!J9 -> 76650 | ... N18: =VC!$C$14*'CB Yr. 2'!N9 -> 76650 | O18: =SUM(C18:N18) -> 919800
B19: Cash Expenses | C19: =FC!$D$13/12 -> 15716.667 | D19: =FC!$D$13/12 -> 15716.667 | E19: =FC!$D$13/12 -> 15716.667 | F19: =FC!$D$13/12 -> 15716.667 | G19: =FC!$D$13/12 -> 15716.667 | H19: =FC!$D$13/12 -> 15716.667 | I19: =FC!$D$13/12 -> 15716.667 | J19: =FC!$D$13/12 -> 15716.667 | ... N19: =FC!$D$13/12 -> 15716.667 | O19: =SUM(C19:N19) -> 188600
B20: Interest | C20: =IS!$D$19/12 -> 1826.6 | D20: =IS!$D$19/12 -> 1826.6 | E20: =IS!$D$19/12 -> 1826.6 | F20: =IS!$D$19/12 -> 1826.6 | G20: =IS!$D$19/12 -> 1826.6 | H20: =IS!$D$19/12 -> 1826.6 | I20: =IS!$D$19/12 -> 1826.6 | J20: =IS!$D$19/12 -> 1826.6 | ... N20: =IS!$D$19/12 -> 1826.6 | O20: =SUM(C20:N20) -> 21919.2
B21: A/P Expenses | C21: =FC!$C$20/12 -> 5450 | D21: =FC!$D$20/12 -> 5616.6667 | E21: =FC!$D$20/12 -> 5616.6667 | F21: =FC!$D$20/12 -> 5616.6667 | G21: =FC!$D$20/12 -> 5616.6667 | H21: =FC!$D$20/12 -> 5616.6667 | I21: =FC!$D$20/12 -> 5616.6667 | J21: =FC!$D$20/12 -> 5616.6667 | K21: =FC!$D$20/12 -> 5616.6667 | ... N21: =FC!$D$20/12 -> 5616.6667 | O21: =SUM(C21:N21) -> 67233.333
B22: Liquor License | C22: 1200 | O22: =SUM(C22:N22) -> 1200
B23: Bonus | D23: =FC!D24 -> 0 | O23: =SUM(C23:N23) -> 0
B24: Tax | D24: =IS!$C$21 -> 54.8 | O24: =SUM(C24:N24) -> 54.8
B25: Loan Repayment | N25: 200892.67 | O25: =SUM(C25:N25) -> 200892.67
B26: Total Outflows | C26: =SUM(C18:C25) -> 100843.27 | D26: =SUM(D18:D25) -> 99864.733 | E26: =SUM(E18:E25) -> 99809.933 | F26: =SUM(F18:F25) -> 99809.933 | G26: =SUM(G18:G25) -> 99809.933 | H26: =SUM(H18:H25) -> 99809.933 | I26: =SUM(I18:I25) -> 99809.933 | J26: =SUM(J18:J25) -> 99809.933 | ... O26: =SUM(O18:O25) -> 1399700
B27: Net Cash Flow | C27: =C14-C26 -> 15523.4 | D27: =D14-D26 -> 16801.933 | E27: =E14-E26 -> 16856.733 | F27: =F14-F26 -> 16856.733 | G27: =G14-G26 -> 16856.733 | H27: =H14-H26 -> 16856.733 | I27: =I14-I26 -> 16856.733 | J27: =J14-J26 -> 16856.733 | ... O27: =O14-O26 -> 0
B28: Beginning Cash | C28: =BS!D8 -> 20000 | D28: =C29 -> 35523.4 | E28: =D29 -> 52325.333 | F28: =E29 -> 69182.067 | G28: =F29 -> 86038.8 | H28: =G29 -> 102895.53 | I28: =H29 -> 119752.27 | J28: =I29 -> 136609 | K28: =J29 -> 153465.73 | ... N28: =M29 -> 204035.93 | O28: =BS!D8 -> 20000
B29: Ending Cash | C29: =SUM(C27:C28) -> 35523.4 | D29: =SUM(D27:D28) -> 52325.333 | E29: =SUM(E27:E28) -> 69182.067 | F29: =SUM(F27:F28) -> 86038.8 | G29: =SUM(G27:G28) -> 102895.53 | H29: =SUM(H27:H28) -> 119752.27 | I29: =SUM(I27:I28) -> 136609 | J29: =SUM(J27:J28) -> 153465.73 | ... O29: =SUM(O27:O28) -> 20000

Sheet CB Yr. 3
B2: Rosa's Palas Franchise
B4: ANNUAL CASH BUDGET
B6: Year 3
C8: March | D8: April | E8: May | F8: June | G8: July | H8: August | I8: September | J8: October | K8: November | L8: December | M8: January | N8: February | O8: Totals
B9: Sales | C9: =IS!$E$12/12 -> 126666.67 | D9: =IS!$E$12/12 -> 126666.67 | E9: =IS!$E$12/12 -> 126666.67 | F9: =IS!$E$12/12 -> 126666.67 | G9: =IS!$E$12/12 -> 126666.67 | H9: =IS!$E$12/12 -> 126666.67 | I9: =IS!$E$12/12 -> 126666.67 | J9: =IS!$E$12/12 -> 126666.67 | ... N9: =IS!$E$12/12 -> 126666.67 | O9: =SUM(C9:N9) -> 1520000
B11: Inflows:
B12: Collections | C12: =C9-(C9*60%*5%) -> 122866.67 | D12: =D9-(D9*60%*5%) -> 122866.67 | E12: =E9-(E9*60%*5%) -> 122866.67 | F12: =F9-(F9*60%*5%) -> 122866.67 | G12: =G9-(G9*60%*5%) -> 122866.67 | H12: =H9-(H9*60%*5%) -> 122866.67 | I12: =I9-(I9*60%*5%) -> 122866.67 | J12: =J9-(J9*60%*5%) -> 122866.67 | ... N12: =N9-(N9*60%*5%) -> 122866.67 | O12: =SUM(C12:N12) -> 1474400
B13: Non-Bank Credit Cards | C13: ='CB Yr. 2'!N9*60%*5% -> 3500 | D13: =C9*60%*5% -> 3800 | E13: =D9*60%*5% -> 3800 | F13: =E9*60%*5% -> 3800 | G13: =F9*60%*5% -> 3800 | H13: =G9*60%*5% -> 3800 | I13: =H9*60%*5% -> 3800 | J13: =I9*60%*5% -> 3800 | K13: =J9*60%*5% -> 3800 | ... N13: =M9*60%*5% -> 3800 | O13: =SUM(C13:N13) -> 45300
B14: Total Inflows | C14: =SUM(C12:C13) -> 126366.67 | D14: =SUM(D12:D13) -> 126666.67 | E14: =SUM(E12:E13) -> 126666.67 | F14: =SUM(F12:F13) -> 126666.67 | G14: =SUM(G12:G13) -> 126666.67 | H14: =SUM(H12:H13) -> 126666.67 | I14: =SUM(I12:I13) -> 126666.67 | J14: =SUM(J12:J13) -> 126666.67 | ... O14: =SUM(O12:O13) -> 1519700
B16: Outflows:
B17: Expenses
B18: Variable Costs | C18: =C9*VC!$C$14 -> 83220 | D18: =D9*VC!$C$14 -> 83220 | E18: =E9*VC!$C$14 -> 83220 | F18: =F9*VC!$C$14 -> 83220 | G18: =G9*VC!$C$14 -> 83220 | H18: =H9*VC!$C$14 -> 83220 | I18: =I9*VC!$C$14 -> 83220 | J18: =J9*VC!$C$14 -> 83220 | ... N18: =N9*VC!$C$14 -> 83220 | O18: =SUM(C18:N18) -> 998640
B19: Cash Expenses | C19: =FC!$E$13/12 -> 15716.667 | D19: =FC!$E$13/12 -> 15716.667 | E19: =FC!$E$13/12 -> 15716.667 | F19: =FC!$E$13/12 -> 15716.667 | G19: =FC!$E$13/12 -> 15716.667 | H19: =FC!$E$13/12 -> 15716.667 | I19: =FC!$E$13/12 -> 15716.667 | J19: =FC!$E$13/12 -> 15716.667 | ... N19: =FC!$E$13/12 -> 15716.667 | O19: =SUM(C19:N19) -> 188600
B20: Interest | C20: =IS!$E$19/12 -> 487.31556 | D20: =IS!$E$19/12 -> 487.31556 | E20: =IS!$E$19/12 -> 487.31556 | F20: =IS!$E$19/12 -> 487.31556 | G20: =IS!$E$19/12 -> 487.31556 | H20: =IS!$E$19/12 -> 487.31556 | I20: =IS!$E$19/12 -> 487.31556 | J20: =IS!$E$19/12 -> 487.31556 | ... N20: =IS!$E$19/12 -> 487.31556 | O20: =SUM(C20:N20) -> 5847.7867
B21: A/P Expenses | C21: =FC!$D$20/12 -> 5616.6667 | D21: =FC!$E$20/12 -> 5783.3333 | E21: =FC!$E$20/12 -> 5783.3333 | F21: =FC!$E$20/12 -> 5783.3333 | G21: =FC!$E$20/12 -> 5783.3333 | H21: =FC!$E$20/12 -> 5783.3333 | I21: =FC!$E$20/12 -> 5783.3333 | J21: =FC!$E$20/12 -> 5783.3333 | K21: =FC!$E$20/12 -> 5783.3333 | ... N21: =FC!$E$20/12 -> 5783.3333 | O21: =SUM(C21:N21) -> 69233.333
B22: Liquor License | C22: =FC!E23 -> 1200 | O22: =SUM(C22:N22) -> 1200
B23: Bonus | D23: =FC!E24 -> 0 | O23: =SUM(C23:N23) -> 0
B24: Tax | D24: =IS!D21 -> 30238.944 | O24: =SUM(C24:N24) -> 30238.944
B25: Loan Repayment | N25: =BS!F21 -> 73097.333 | O25: =SUM(C25:N25) -> 73097.333
B26: Total Outflows | C26: =SUM(C18:C25) -> 106240.65 | D26: =SUM(D18:D25) -> 135446.26 | E26: =SUM(E18:E25) -> 105207.32 | F26: =SUM(F18:F25) -> 105207.32 | G26: =SUM(G18:G25) -> 105207.32 | H26: =SUM(H18:H25) -> 105207.32 | I26: =SUM(I18:I25) -> 105207.32 | J26: =SUM(J18:J25) -> 105207.32 | ... O26: =SUM(O18:O25) -> 1366857.4
B27: Net Cash Flow | C27: =C14-C26 -> 20126.018 | D27: =D14-D26 -> -8779.5929 | E27: =E14-E26 -> 21459.351 | F27: =F14-F26 -> 21459.351 | G27: =G14-G26 -> 21459.351 | H27: =H14-H26 -> 21459.351 | I27: =I14-I26 -> 21459.351 | J27: =J14-J26 -> 21459.351 | ... O27: =O14-O26 -> 152842.6
B28: Beginning Cash | C28: =BS!F8 -> 20000 | D28: =C29 -> 40126.018 | E28: =D29 -> 31346.425 | F28: =E29 -> 52805.776 | G28: =F29 -> 74265.127 | H28: =G29 -> 95724.478 | I28: =H29 -> 117183.83 | J28: =I29 -> 138643.18 | K28: =J29 -> 160102.53 | ... N28: =M29 -> 224480.58 | O28: =BS!F8 -> 20000
B29: Ending Cash | C29: =SUM(C27:C28) -> 40126.018 | D29: =SUM(D27:D28) -> 31346.425 | E29: =SUM(E27:E28) -> 52805.776 | F29: =SUM(F27:F28) -> 74265.127 | G29: =SUM(G27:G28) -> 95724.478 | H29: =SUM(H27:H28) -> 117183.83 | I29: =SUM(I27:I28) -> 138643.18 | J29: =SUM(J27:J28) -> 160102.53 | ... O29: =SUM(O27:O28) -> 172842.6

Sheet BS
B2: Rosa's Palas Franchise
B4: Three-Year Statement of Financial Position Projections
C6: Year 1 | E6: Year 2 | G6: Year 3
B7: ASSETS
B8: Cash | D8: ='CB Yr.1'!O37 -> 20000 | F8: ='CB Yr. 2'!O29 -> 20000 | H8: ='CB Yr. 3'!O29 -> 172842.6
B9: Receivables | D9: =('CB Yr.1'!N9*60%)*5% -> 3200 | F9: ='CB Yr. 2'!N9*60%*5% -> 3500 | H9: ='CB Yr. 3'!N9*60%*5% -> 3800
B10: Inventory | D10: 15000 | F10: =Investments!C8 -> 15000 | H10: =Investments!C8 -> 15000
B11: Fixed Assets | C11: =(Investments!C10) -> 390000 | E11: =Investments!C10 -> 390000 | G11: =Investments!C10 -> 390000
B12: Less: Accumulated Depreciation | C12: =-FC!C28 -> -139286 | D12: =C11+C12 -> 250714 | E12: =C12-FC!D28 -> -210919 | F12: =SUM(E11:E12) -> 179081 | G12: =E12-FC!E28 -> -270613 | H12: =SUM(G11,G12) -> 119387
B13: Net Franchise Fee | D13: =Investments!C6-FC!C29 -> 40000 | F13: =Investments!C6-(SUM(FC!C29:D29)) -> 30000 | H13: =Investments!C6-(SUM(FC!C29:E29)) -> 20000
B14: Net Liquor License | D14: =Investments!C7-FC!C30 -> 800 | F14: =Investments!C7-(SUM(FC!C30:D30)) -> 600 | H14: =Investments!C7-(SUM(FC!C30:E30)) -> 400
B15: Total Assets | D15: =SUM(D8:D14) -> 329714 | F15: =SUM(F8:F14) -> 248181 | H15: =SUM(H8:H14) -> 331429.6
B17: LIABILITIES AND EQUITY
B18: Accounts Payable | D18: =FC!C20/12 -> 5450 | F18: =FC!D20/12 -> 5616.6667 | H18: =FC!E20/12 -> 5783.3333
B19: Bonus Payable | D19: =FC!C24 -> 0 | F19: =FC!D24 -> 0 | H19: =FC!E24 -> 0
B20: Tax Payable | D20: =IS!C21 -> 54.8 | F20: =IS!D21 -> 30238.944 | H20: =IS!E21 -> 62480.742
B21: Bank Loan | D21: =Investments!C14-'CB Yr.1'!$N$33 -> 273990 | F21: =D21-'CB Yr. 2'!N25 -> 73097.333 | H21: =F21-'CB Yr. 3'!N25 -> 0
B22: Total Liabilities | D22: =SUM(D18:D21) -> 279494.8 | F22: =SUM(F18:F21) -> 108952.94 | H22: =SUM(H18:H21) -> 68264.076
B24: Common Stock | D24: =Investments!C13 -> 50000 | F24: =Investments!C13 -> 50000 | H24: =Investments!C13 -> 50000
B25: Retained Earnings | D25: =IS!C22 -> 219.2 | F25: =D25+IS!D22 -> 89228.056 | H25: =F25+IS!E22 -> 213165.53
B26: Total Equity | D26: =SUM(D24:D25) -> 50219.2 | F26: =SUM(F24:F25) -> 139228.06 | H26: =SUM(H24:H25) -> 263165.53
B28: Total Liabilities and Equity | D28: =SUM(D22,D26) -> 329714 | F28: =SUM(F22,F26) -> 248181 | H28: =SUM(H22,H26) -> 331429.6
B31: CASH NEEDS TO MATCH WHAT WE HAVE ON CASH BUDGET!
B32: NO PLUGS OR PAYABLES TO MAKE THINGS BALANCE!
B33: IF DO ALL 3 STATEMENTS BS WILL BALANCE!
B34: IF BS WONT BALANCE, GO BACK DO DEBITS AND CREDITS (SUPER T)
B35: NEXT CLASS DO LOTS! AOF ANALYSIS

Sheet Break-Even
B2: Rosa's Palas Franchise
B4: Break-Even Analysis
B6: Break-Even | C6: Year 1 | D6: Year 2 | E6: Year 3
B7: Total Fixed Costs | C7: =FC!C38 -> 438766 | D7: =FC!D38 -> 360952.2 | E7: =FC!E38 -> 334941.79
B8: Contribution Margin | C8: =VC!$C$16 -> 0.343 | D8: =VC!$C$16 -> 0.343 | E8: =VC!$C$16 -> 0.343
B9: B/E Sales ($) | C9: =C7/C8 -> 1279201.2 | D9: =D7/D8 -> 1052338.8 | E9: =E7/E8 -> 976506.67
B11: Projected Sales | C11: =IS!C9 -> 1280000 | D11: =IS!D9 -> 1400000 | E11: =IS!E9 -> 1520000
B12: Margin of Safety | C12: =(C11-C9)/C11 -> 0.00062408892 | D12: =(D11-D9)/D11 -> 0.24832945 | E12: =(E11-E9)/E11 -> 0.3575614
B14: Cash Break-Even | C14: Year 1 | D14: Year 2 | E14: Year 3
B15: Total Cash Fixed Costs | C15: =FC!C13 -> 188600 | D15: =FC!D13 -> 188600 | E15: =FC!E13 -> 188600
B16: Contribution Margin | C16: =VC!$C$16 -> 0.343 | D16: =VC!$C$16 -> 0.343 | E16: =VC!$C$16 -> 0.343
B17: Cash B/E Sales ($) | C17: =C15/C16 -> 549854.23 | D17: =D15/D16 -> 549854.23 | E17: =E15/E16 -> 549854.23
B19: Projected Sales | C19: =IS!C9 -> 1280000 | D19: =IS!D9 -> 1400000 | E19: =IS!E9 -> 1520000
B20: Margin of Safety | C20: =(C19-C17)/C19 -> 0.57042638 | D20: =(D19-D17)/D19 -> 0.60724698 | E20: =(E19-E17)/E19 -> 0.6382538

Sheet ROI
B2: Rosa's Palas Franchise
B4: Return Analysis
B6: Return on Investment | C6: Year 1 | D6: Year 2 | E6: Year 3
B7: Net Income | C7: =IS!C22 -> 219.2 | D7: =IS!D22 -> 89008.856 | E7: =IS!E22 -> 123937.47
B8: Investments | C8: =Investments!$C$11 -> 476000 | D8: =Investments!$C$11 -> 476000 | E8: =Investments!$C$11 -> 476000
B9: ROI | C9: =C7/C8 -> 0.0004605042 | D9: =D7/D8 -> 0.18699339 | E9: =E7/E8 -> 0.26037284
B11: Return on Equity | C11: Year 1 | D11: Year 2 | E11: Year 3
B12: Net Income | C12: =IS!C22 -> 219.2 | D12: =IS!D22 -> 89008.856 | E12: =IS!E22 -> 123937.47
B13: Equity | C13: =BS!D26+BS!D27 -> 50219.2 | D13: =Investments!$C$13 -> 50000 | E13: =Investments!$C$13 -> 50000
B14: ROE | C14: =C12/C13 -> 0.0043648644 | D14: =D12/D13 -> 1.7801771 | E14: =E12/E13 -> 2.4787494
