Workbook

Sheet INCOME STATEMENT
A1: TERRACYCLE INC.
B3: 2005 | E3: 2004
A4: REVENUE
A5: Sales | B5: 461665 | C5: 1 | E5: 104470 | F5: 1
A6: Less: Cost of Goods Sold | B6: -487524 | C6: =B6/B5 -> -1.0560125 | E6: -150113 | F6: =E6/E5 -> -1.4369005
A7: Gross Profit | B7: =B5+B6 -> -25859 | C7: =B7/B5 -> -0.056012477 | E7: =E5+E6 -> -45643 | F7: =F5+F6 -> -0.43690055
A9: OPERATING EXPENSES
A10: Salaries | B10: 579887 | C10: =B10/$B$5 -> 1.2560775 | E10: 335142 | F10: =E10/$E$5 -> 3.2080214
A11: Office & Administrative | B11: 33585 | C11: =B11/$B$5 -> 0.072747555 | E11: 67342 | F11: =E11/$E$5 -> 0.64460611
A12: Insurance | B12: 43815 | C12: =B12/$B$5 -> 0.09490648 | E12: 13868 | F12: =E12/$E$5 -> 0.13274624
A13: Advertising | B13: 75283 | C13: =B13/$B$5 -> 0.16306846 | E13: 26815 | F13: =E13/$E$5 -> 0.25667656
A14: Research & Development | B14: 14267 | C14: =B14/$B$5 -> 0.030903361 | E14: 20775 | F14: =E14/$E$5 -> 0.19886092
A15: Property Overhead | B15: 92846 | C15: =B15/$B$5 -> 0.2011112 | E15: 36942 | F15: =E15/$E$5 -> 0.35361348
A16: Telephone & Communications | B16: 23632 | C16: =B16/$B$5 -> 0.051188632 | E16: 19492 | F16: =E16/$E$5 -> 0.18657988
A17: Professional Fees/Licenses | B17: 47138 | C17: =B17/$B$5 -> 0.10210434 | E17: 79555 | F17: =E17/$E$5 -> 0.76151048
A18: Travel/Vehicles | B18: 74514 | C18: =B18/$B$5 -> 0.16140275 | E18: 82909 | F18: =E18/$E$5 -> 0.79361539
A19: Interest Expense | B19: 18218 | C19: =B19/$B$5 -> 0.039461514 | E19: 1643 | F19: =E19/$E$5 -> 0.015727003
A20: Amortization | B20: 30766 | C20: =B20/$B$5 -> 0.066641396 | E20: 5098 | F20: =E20/$E$5 -> 0.048798698
A21: Miscellaneous | B21: 1818 | C21: =B21/$B$5 -> 0.0039379204 | E21: 1300 | F21: =E21/$E$5 -> 0.012443764
A22: Less:Total Operating Expenses | B22: =SUM(B10:B21) -> 1035769 | C22: =SUM(C10:C21) -> 2.2435511 | E22: =SUM(E10:E21) -> 690881 | F22: =E22/E5 -> 6.6132
A24: Net Income Before taxes | B24: =B7-B22 -> -1061628 | C24: =B24/B5 -> -2.2995635 | E24: =E7-E22 -> -736524 | F24: =E24/E5 -> -7.0501005
A25: Income taxes | B25: 0 | C25: =B25/B5 -> 0 | E25: 0 | F25: =E25/E6 -> 0
A27: NET INCOME AFTER TAX | B27: =B24-B25 -> -1061628 | C27: =B27/B5 -> -2.2995635 | E27: =E24-E25 -> -736524 | F27: =E27/E5 -> -7.0501005

Sheet BALANCE SHEET
A1: TERRACYCLE INC.
B2: 2005 | D2: 2004
A3: ASSETS
A4: Current Assets:
A5: Cash | B5: 120929 | D5: 83941
A6: Accounts Receivable | B6: 267691 | D6: 20561
A7: Due from Shareholder | B7: 75000 | D7: 0
A8: Inventory | B8: 421980 | D8: 81605
A9: Prepaid Expenses | B9: 30600 | D9: 55825
A10: Total Current Assets | C10: =SUM(B5:B9) -> 916200 | E10: =SUM(D5:D9) -> 241932
A12: Long-Term Asset:
A13: Fixed Assets | B13: 151712 | D13: 94341
A14: Less Accumulated Amortization | B14: -57405 | C14: =B13+B14 -> 94307 | D14: -30577 | E14: =D13+D14 -> 63764
A15: Patents & Trademarks | B15: 42059 | D15: 26560
A16: Less: Accumulated Amortization | B16: -4545 | C16: =B15+B16 -> 37514 | D16: -2775 | E16: =D15+D16 -> 23785
A17: Total Long-Term Assets | C17: =C14+C16 -> 131821 | E17: =E14+E16 -> 87549
A19: TOTAL ASSETS | C19: =C17+C10 -> 1048021 | E19: =E10+E17 -> 329481
A21: LIABILITIES & SHAREHODLERS' EQUITY
A22: Current Liabilities
A23: Accounts Payable | B23: 228020 | D23: 52565
A24: Salaries Payable | B24: 48927 | D24: 0
A25: Insurance Payable | B25: 21348 | D25: 15550
A26: Demand Loan | B26: 149988 | D26: 0
A27: Total Current Assets | C27: =SUM(B23:B26) -> 448283 | E27: =SUM(D23:D26) -> 68115
A29: Shareholders' Equity
A30: Common Stock | B30: 292011 | D30: 292011
A31: Series A Preferred Stock | B31: 1117000 | D31: =B31 -> 1117000
A32: Series B Preferred Stock | B32: 1500000 | D32: 100000
A33: Retained Earnings | B33: -2309273 | D33: -1247645
A34: Total Shareholders' Equity | C34: =SUM(B30:B33) -> 599738 | E34: =SUM(D30:D33) -> 261366
A36: TOTAL LIABILITIES & SHAREHOLDERS' EQUITY | C36: =C27+C34 -> 1048021 | E36: =E27+E34 -> 329481

Sheet CASH FLOW STATEMENT
A1: TERRACYCLE INC.
A3: Net Loss | C3: ='INCOME STATEMENT'!B27 -> -1061628
A5: Operations
A6: Amortization | B6: ='INCOME STATEMENT'!B20 -> 30766 | E6: Retained Earnings
A7: ='BALANCE SHEET'!A6 -> Accounts Receivable | B7: ='BALANCE SHEET'!D6-'BALANCE SHEET'!B6 -> -247130 | E7: =-'BALANCE SHEET'!D33 -> 1247645 | F7: O/B
A8: ='BALANCE SHEET'!A8 -> Inventory | B8: ='BALANCE SHEET'!D8-'BALANCE SHEET'!B8 -> -340375 | E8: =-C3 -> 1061628 | F8: Net Loss
A9: ='BALANCE SHEET'!A9 -> Prepaid Expenses | B9: ='BALANCE SHEET'!D9-'BALANCE SHEET'!B9 -> 25225 | E9: =E7+E8 -> 2309273 | F9: T/B
A10: ='BALANCE SHEET'!A23 -> Accounts Payable | B10: ='BALANCE SHEET'!B23-'BALANCE SHEET'!D23 -> 175455 | E10: 0 | F10: Dividends
A11: ='BALANCE SHEET'!A24 -> Salaries Payable | B11: ='BALANCE SHEET'!B24-'BALANCE SHEET'!D24 -> 48927 | E11: =-'BALANCE SHEET'!B33 -> 2309273 | F11: E/B
A12: ='BALANCE SHEET'!A25 -> Insurance Payable | B12: ='BALANCE SHEET'!B25-'BALANCE SHEET'!D25 -> 5798 | C12: =SUM(B6:B12) -> -301334
A14: Net Cash Flow From Operations | C14: =C3+C12 -> -1362962
A16: Financing
A17: Demand Loan | B17: ='BALANCE SHEET'!B26-'BALANCE SHEET'!D26 -> 149988
A18: ='BALANCE SHEET'!A7 -> Due from Shareholder | B18: ='BALANCE SHEET'!D7-'BALANCE SHEET'!B7 -> -75000 | E18: Fixed Assets
A19: ='BALANCE SHEET'!A30 -> Common Stock | B19: ='BALANCE SHEET'!B30-'BALANCE SHEET'!D30 -> 0 | E19: ='BALANCE SHEET'!E17 -> 87549 | F19: O/B
A20: ='BALANCE SHEET'!A31 -> Series A Preferred Stock | B20: ='BALANCE SHEET'!B31-'BALANCE SHEET'!D31 -> 0 | E20: Dep'n | F20: =B6 -> 30766
A21: ='BALANCE SHEET'!A32 -> Series B Preferred Stock | B21: ='BALANCE SHEET'!B32-'BALANCE SHEET'!D32 -> 1400000 | E21: =E19-F20 -> 56783 | F21: T/B
A22: Dividends Declared | B22: =E10 -> 0 | C22: =SUM(B17:B22) -> 1474988 | E22: =E23-E21 -> 75038 | F22: Purchases
E23: ='BALANCE SHEET'!C17 -> 131821 | F23: E/B
A24: Investing
A25: Fixed Asset Purchases | C25: =-E22 -> -75038
A27: Net Cash Flow | C27: =C14+C22+C25 -> 36988
A28: Beginning Cash | C28: ='BALANCE SHEET'!D5 -> 83941
A29: Ending Cash | C29: =C27+C28 -> 120929

Sheet DIFFERENTIAL
A1: TERRACYCLE INC
F2: UNIT COST PER BOTTLE
B3: ASSUMPTIONS | C3: 30000 | D3: 110000
A4: INFLOWS | F4: AFRICAN VIOLET | I4: ORCHID PLANT
A5: Sales | B5: 2.84 per bottle | C5: =C3*2.84 -> 85200 | D5: =D3*2.84 -> 312400 | F5: Bottle | G5: 0.35 | I5: Bottle | J5: 0.35
F6: Safety Cap | G6: 0.07 | I6: Spray Head | J6: 0.27
A7: OUTFLOWS | F7: Direct Labour | G7: 0.85 | I7: Direct Labour | J7: 0.85
A8: COGS | B8: Unit Cost/Bottle*Number Sold | C8: =(G12*(C3/2))+(J12*(C3/2)) -> 72489.375 | D8: =(G12*(D3/2))+(J12*(D3/2)) -> 265794.38 | F8: Brewing | G8: =1.97/128*20 -> 0.3078125 | I8: Brewing | J8: =1.97/128*20 -> 0.3078125 | L8: ***Brewing: 1.97/128 ounces per gallon*20 ounces per bottle
A9: Promotions | B9: 10,000 per product (cut to 25% if sales low) | C9: =10000*2*0.25 -> 5000 | D9: =10000*2 -> 20000 | F9: Packaging | G9: 0.4 | I9: Packaging | J9: 0.4
A10: Total Outflows | C10: =C8+C9 -> 77489.375 | D10: =D8+D9 -> 285794.38 | F10: English Labels | G10: =0.15*0.7 -> 0.105 | I10: English Labels | J10: =0.44*0.5 -> 0.22 | L10: ***English Labels: Price per label*percentage sold in US
F11: English/French | G11: =0.44*0.3 -> 0.132 | I11: English/French | J11: =0.44*0.5 -> 0.22 | L11: ***English/French Labels: Price per label*percentage sold in Canada
A12: NET CASH FLOW | C12: =C5-C10 -> 7710.625 | D12: =D5-D10 -> 26605.625 | F12: Total | G12: =SUM(G5:G11) -> 2.2148125 | I12: Total | J12: =SUM(J5:J11) -> 2.6178125
A14: INVESTMENTS | F14: Average COGS
A15: Accounts Receivable | B15: Differential Sales/360*60 days | C15: =C5/360*60 -> 14200 | D15: =D5/360*60 -> 52066.667 | F15: (2.21+2.62)/2
A16: Inventory | B16: Differential COGS/360*85 days | C16: =C8/360*85 -> 17115.547 | D16: =D8/360*85 -> 62757.005 | F16: =(G12+J12)/2 -> 2.4163125
A17: Accounts Payable | B17: Differential COGS/360*64 days | C17: =-C8/360*64 -> -12887 | D17: =-D8/360*64 -> -47252.333
A18: TOTAL INVESTMENTS | C18: =SUM(C15:C17) -> 18428.547 | D18: =SUM(D15:D17) -> 67571.339 | F18: Days Of A/R
F19: Last Year's A/R/(Last Year's Sales/360)
A20: ROI | B20: NCF/Total Investments | C20: =C12/C18 -> 0.41840657 | D20: =D12/D18 -> 0.39374128 | F20: ='BALANCE SHEET'!B6/('INCOME STATEMENT'!B5/360) -> 208.74175
A21: PAYBACK | B21: Total Investments/NCF | C21: =C18/C12 -> 2.3900199 | D21: =D18/D12 -> 2.5397388
A23: Breakeven | B23: Fixed Costs + Investment/Unit Contribution | C23: =(C18+C9)/(2.84-F16) -> 55296.762 | D23: =(D18+D9)/(2.84-F16) -> 206688.51
A24: Low: | B24: (18,429+5,000)/(2.84-2.416)
A25: High: | B25: (67,571+20,000)/(2.84-2.416)
A27: What if they increase their price to $3.00? | C27: =(C18+C9)/(3-$F$16) -> 40138.853 | D27: =(D18+D9)/(3-$F$16) -> 150031.2
A29: What if they increase their price to $2.89? | C29: =(C18+C9)/(2.89-$F$16) -> 49459.922 | D29: =(D18+D9)/(2.89-$F$16) -> 184871.54

Sheet PROJECTED INCOME STATEMENT
A1: TERRACYCLE INC
B3: ASSUMPTIONS | C3: 2005 | E3: LOW | G3: HIGH | I3: STATUS QUO
A4: Revenue
A5: Sales | B5: ((461,665-104,470)/104,470)/2=171% growth | C5: 461665 | E5: =C5*2.71 -> 1251112.1 | G5: =C5*2.71 -> 1251112.1 | I5: =C5*2.71 -> 1251112.1
A6: New Sales (Differential) | B6: taken from differential | E6: =DIFFERENTIAL!C5 -> 85200 | G6: =DIFFERENTIAL!D5 -> 312400 | I6: 0
A7: Less: Cost of Goods Sold | B7: 65% of existing sales | C7: -487524 | E7: =-E5*0.65 -> -813222.9 | G7: =-G5*0.65 -> -813222.9 | I7: =-I5*0.65 -> -813222.9
A8: Less: New Cost of Goods Sold (differential) | B8: taken from differential | E8: =-DIFFERENTIAL!C8 -> -72489.375 | G8: =-DIFFERENTIAL!D8 -> -265794.38 | I8: 0
A9: Gross Profit | C9: =C5+C7 -> -25859 | E9: =SUM(E5:E8) -> 450599.88 | G9: =SUM(G5:G8) -> 484494.88 | I9: =I5+I7 -> 437889.25
A11: Operating Expenses | B11: (1035769-690881)/690881=50% Growth | C11: 1035769 | E11: =C11*1.5 -> 1553653.5 | G11: =C11*1.5 -> 1553653.5 | I11: =C11*1.5 -> 1553653.5
A12: Promotions | B12: taken from differential | E12: =DIFFERENTIAL!C9 -> 5000 | G12: =DIFFERENTIAL!D9 -> 20000 | I12: 0
A13: Total Operating Expenses | C13: =C11+C12 -> 1035769 | E13: =E11+E12 -> 1558653.5 | G13: =G11+G12 -> 1573653.5 | I13: =I11+I12 -> 1553653.5
A15: Net Income Before Tax | C15: =C9-C13 -> -1061628 | E15: =E9-E13 -> -1108053.6 | G15: =G9-G13 -> -1089158.6 | I15: =I9-I13 -> -1115764.2
A16: Income taxes | B16: net loss, no tax | C16: 0 | E16: 0 | G16: 0 | I16: 0
A17: Net Income After Tax | C17: =C15-C16 -> -1061628 | E17: =E15+E16 -> -1108053.6 | G17: =G15+G16 -> -1089158.6 | I17: =I15-I16 -> -1115764.2

Sheet PROJECTED BALANCE SHEET
A1: TERRACYCLE INC.
O3: 2004 Days of A/R:
O4: A/R/(Sales/360)
B5: ASSUMPTIONS | C5: 2005 | F5: LOW | I5: HIGH | L5: STATUS QUO | O5: ='BALANCE SHEET'!D6/('INCOME STATEMENT'!E5/360) -> 70.852494
A6: ASSETS
A7: Current Assets | O7: 2005 Days of Inventory
A8: Cash | B8: assume same amount | C8: 120929 | F8: =C8 -> 120929 | I8: =C8 -> 120929 | L8: =C8 -> 120929 | O8: Inventory/(COGS/360)
A9: Accounts Receivable | B9: 70.85 days (Existing) + Diff. A/R | C9: 267691 | F9: =(('PROJECTED INCOME STATEMENT'!E5/360)*'PROJECTED BALANCE SHEET'!O5)+DIFFERENTIAL!C15 -> 260434.49 | I9: =(('PROJECTED INCOME STATEMENT'!G5/360)*'PROJECTED BALANCE SHEET'!O5)+DIFFERENTIAL!D15 -> 298301.15 | L9: ='PROJECTED INCOME STATEMENT'!I5/360*'PROJECTED BALANCE SHEET'!O5 -> 246234.49 | O9: ='BALANCE SHEET'!B8/(-'INCOME STATEMENT'!B6/360) -> 311.60066
A10: Due from Shareholder | B10: anticipated would be collected | C10: 75000 | F10: 0 | I10: 0 | L10: 0
A11: Inventory | B11: 311.6 days (Existing) + Diff. Inventory | C11: 421980 | F11: =((-'PROJECTED INCOME STATEMENT'!E7/360)*'PROJECTED BALANCE SHEET'!O9)+DIFFERENTIAL!C16 -> 721006.63 | I11: =((-'PROJECTED INCOME STATEMENT'!G7/360)*'PROJECTED BALANCE SHEET'!O9)+DIFFERENTIAL!D16 -> 766648.09 | L11: =-'PROJECTED INCOME STATEMENT'!I7/360*'PROJECTED BALANCE SHEET'!O9 -> 703891.09
A12: Prepaid Expenses | B12: increase by 50% | C12: 30600 | F12: =C12*1.5 -> 45900 | I12: =C12*1.5 -> 45900 | L12: =C12*1.5 -> 45900
A13: Total Current Assets | D13: =SUM(C8:C12) -> 916200 | G13: =SUM(F8:F12) -> 1148270.1 | J13: =SUM(I8:I12) -> 1231778.2 | M13: =SUM(L8:L12) -> 1116954.6
A15: Long-Term Assets
A16: Fixed Assets | B16: added 47,710 additional assets, given | C16: 151712 | F16: =C16+47710 -> 199422 | I16: =C16+47710 -> 199422 | L16: =C16+47710 -> 199422
A17: Less: Accum. Amort. Fixed Assets | B17: added 28,475 amortization, given | C17: -57405 | D17: =C16+C17 -> 94307 | F17: =C17-28475 -> -85880 | G17: =F16+F17 -> 113542 | I17: =C17-28475 -> -85880 | J17: =I16+I17 -> 113542 | L17: =C17-28475 -> -85880 | M17: =L16+L17 -> 113542
A18: Patents & Trademarks | B18: no new purchases | C18: 42059 | F18: 42059 | I18: 42059 | L18: =C18 -> 42059
A19: Less: Accum. Amort. Patents & Trademarks | B19: added 1,770 amortization, given | C19: -4545 | D19: =C18+C19 -> 37514 | F19: =C19-1770 -> -6315 | G19: =F18+F19 -> 35744 | I19: =C19-1770 -> -6315 | J19: =I18+I19 -> 35744 | L19: =C19-1770 -> -6315 | M19: =L18+L19 -> 35744
A20: Total Long-Term Assets | D20: =D17+D19 -> 131821 | G20: =G17+G19 -> 149286 | J20: =J17+J19 -> 149286 | M20: =M17+M19 -> 149286
A22: TOTAL ASSETS | D22: =D20+D13 -> 1048021 | G22: 1105309.4 | J22: 1021801.2 | M22: =M13+M20 -> 1266240.6
A24: LIABILITIES & SHAREHOLDERS' EQUITY
A25: Liabilities
A26: Current Liabilities
A27: Accounts Payable | B27: 168.4 days (Existing) + Diff. A/P | C27: 228020 | F27: =((-'PROJECTED INCOME STATEMENT'!E7/360)*'PROJECTED BALANCE SHEET'!O29)+(-DIFFERENTIAL!C17) -> 393239.73 | I27: =((-'PROJECTED INCOME STATEMENT'!G7/360)*'PROJECTED BALANCE SHEET'!O29)+(-DIFFERENTIAL!D17) -> 427605.06 | L27: =-'PROJECTED INCOME STATEMENT'!I7/360*'PROJECTED BALANCE SHEET'!O29 -> 380352.73 | O27: 2005 Days of A/P
A28: Salaries Payable | B28: same number | C28: 48927 | F28: =C28 -> 48927 | I28: =C28 -> 48927 | L28: =C28 -> 48927 | O28: A/P/(COGS/360)
A29: Insurance Payable | B29: eliminated | C29: 21348 | F29: 0 | I29: 0 | L29: 0 | O29: ='BALANCE SHEET'!B23/(-'INCOME STATEMENT'!B6/360) -> 168.37571
A30: Demand Loan | B30: same number | C30: 149988 | F30: =C30 -> 149988 | I30: =C30 -> 149988 | L30: =C30 -> 149988
A31: Total Current Liabilities | D31: =SUM(C27:C30) -> 448283 | G31: =SUM(F27:F30) -> 592154.73 | J31: =SUM(I27:I30) -> 626520.06 | M31: =SUM(L27:L30) -> 579267.73
A33: Shareholder's Equity
A34: Additional Financing Required | B34: plug | F34: =G39-(SUM(F35:F38)) -> 1021470.2 | I34: =J39-(SUM(I35:I38)) -> 884701.79 | L34: =M39-(SUM(L35:L38)) -> 1202999.1
A35: Common Stock | B35: same number | C35: 292011 | F35: =C35 -> 292011 | I35: =C35 -> 292011 | L35: =C35 -> 292011
A36: Series A Perferred Stock | B36: same number | C36: 1117000 | F36: =C36 -> 1117000 | I36: =C36 -> 1117000 | L36: =C36 -> 1117000
A37: Series B Preferred Stock | B37: same number | C37: 1500000 | F37: =C37 -> 1500000 | I37: =C37 -> 1500000 | L37: =C37 -> 1500000
A38: Retained Earnings | B38: added net loss from proj. Income statement | C38: -2309273 | F38: =C38+'PROJECTED INCOME STATEMENT'!E17 -> -3417326.6 | I38: =C38+'PROJECTED INCOME STATEMENT'!G17 -> -3398431.6 | L38: =C38+'PROJECTED INCOME STATEMENT'!I17 -> -3425037.2
A39: Total Shareholder's Equity | D39: =SUM(C34:C38) -> 599738 | G39: =G41-G31 -> 513154.63 | J39: =J41-J31 -> 395281.17 | M39: =M41-M31 -> 686972.84
A41: TOTAL LIABILITIES & SHAREHOLDERS' EQUITY | D41: =D31+D39 -> 1048021 | G41: =G22 -> 1105309.4 | J41: =J22 -> 1021801.2 | M41: =M22 -> 1266240.6

Sheet Sheet1
