Workbook

Sheet Working T Accounts
A1: UP - IN - SMOKE | I1: UP - IN - SMOKE
A3: Inventory ($) | D3: Inventory (Units) | G3: $/Unit | I3: SPECIFIC IDENTIFICATION
A4: 47438 | B4: O/B | D4: 2875 | E4: O/B | G4: =A4/D4 -> 16.500174
I5: ENDING INVENTORY: | K5: Write down unit price to LCNRV of 18.000
A6: =375*52 -> 19500 | B6: #1001 | D6: 1300 | E6: =B6 -> #1001 | J6: # OF UNITS | K6: UNIT PRICE | L6: PORTION OF E/I
A7: =A6*0.09 -> 1755 | B7: Duty | I7: PURCHASE #1001 | J7: 440 | K7: =G9 -> 16.3712 | L7: =J7*K7 -> 7203.328
A8: =0.53*52 -> 27.56 | B8: Freight | I8: PURCHASE #3005 | J8: 929 | K8: =G17 -> 15.6 | L8: =J8*K8 -> 14492.4
A9: =SUM(A6:A8)-SUM(B6:B8) -> 21282.56 | B9: T #1001 | D9: =D6 -> 1300 | E9: =B9 -> T #1001 | G9: =A9/D9 -> 16.3712 | I9: PURCHASE #2003 | J9: 1239 | K9: 18 | L9: =J9*K9 -> 22302
I10: PURCHASE #1002 | J10: 1650 (ALL) | K10: 18 | L10: =1650*K10 -> 29700
A11: =415*67 -> 27805 | B11: #3004 | D11: 1675 | E11: =B11 -> #3004 | I11: TOTAL ENDING INVENTORY | J11: =SUM(J7:J10) -> 2608 | L11: =SUM(L7:L10) -> 73697.728
A12: Discounts | B12: =A11*0.02 -> 556.1
A13: =A11-B12 -> 27248.9 | B13: T #3004 | D13: =D11 -> 1675 | E13: =B13 -> T #3004 | G13: =A13/D13 -> 16.268 | I13: COST OF GOODS SOLD: | J13: =A33-L11 -> 111655.92
I14: (COGAFS - E/I)
A15: =390*74 -> 28860 | B15: #3005 | D15: 1850 | E15: =B15 -> #3005
I16: DR Cost of Goods Sold Expense | J16: =J13 -> 111655.92
A17: =A15-B16 -> 28860 | B17: T #3005 | D17: =D15 -> 1850 | E17: =B17 -> T #3005 | G17: =A17/D17 -> 15.6 | I17: CR Inventory | K17: =J16 -> 111655.92
A19: =455*64 -> 29120 | B19: #2003 | D19: =64*25 -> 1600 | E19: =B19 -> #2003
A20: =A19*0.12 -> 3494.4 | B20: Duty | I20: COST OF STOLEN CIGARS
A21: =64*0.53 -> 33.92 | B21: Freight
A22: Discounts | B22: =A19*0.03 -> 873.6 | I22: AVERAGE UNIT COST: | J22: =A33/D33 -> 17.122739
A23: Return | B23: =5*455 -> 2275 | D23: Return | E23: 125 | I23: (COGAFS/UAFS)
A24: Return Duty | B24: =0.12*(B23) -> 273
A25: =B23*0.03 -> 68.25 | B25: R. Discount | I25: ENDING INVENTORY IN UNITS:
A26: =SUM(A19:A25)-SUM(B19:B25) -> 29294.97 | B26: T #2003 | D26: =D19-E23 -> 1475 | E26: =B26 -> T #2003 | G26: =A26/D26 -> 19.860997 | I26: 2,608 (physically there) + 1,650 (in transit)
I27: =2608+1650 -> 4258
A28: =66*422 -> 27852 | B28: #1002 | D28: =66*25 -> 1650 | E28: =B28 -> #1002
A29: =66*0.53 -> 34.98 | B29: Freight | I29: UNITS SOLD/STOLEN
A30: =A28*0.12 -> 3342.24 | B30: Duty | I30: UAFS - E/I IN UNITS
A31: =SUM(A28:A30) -> 31229.22 | B31: T #1002 | D31: =D28 -> 1650 | E31: =B31 -> T #1002 | G31: =A31/D31 -> 18.9268 | I31: =D33-I27 -> 6567
A33: =A4+A9+A13+A17+A26+A31 -> 185353.65 | B33: COGAFS (sum) | D33: =D4+D9+D13+D17+D26+D31 -> 10825 | E33: UAFS (sum) | I33: NUMBER OF STOLEN CIGARS:
A34: COGS (dif) | B34: =A33-A35 -> 111655.92 | D34: Sold (given) | E34: 6520 | I34: UNITS SOLD/STOLEN - UNITS SOLD
A35: =L11 -> 73697.728 | B35: E/B from Specific ID | D35: =D33-E34 -> 4305 | E35: T/B | I35: =6567-6520 -> 47
D36: Stolen (dif) | E36: =D35-D37 -> 47
D37: =I27 -> 4258 | E37: E/B from Specific ID+In-transit | I37: COST OF STOLEN CIGARS
I38: AVERAGE UNIT COST * # STOLEN
I39: =J22*I35 -> 804.76873

Sheet Sheet1
A1: Up-In-Smoke Corporation
A3: Purchase #1001
A4: Dr Inventory | F4: ='Working T Accounts'!A9 -> 21282.56
A5: Cr Cash | G5: =F4 -> 21282.56
A7: Purchase #3004
A8: Dr Inventory | F8: ='Working T Accounts'!A13 -> 27248.9
A9: Cr Cash | G9: =F8 -> 27248.9
A11: Purchase #3005
A12: Dr Inventory | F12: ='Working T Accounts'!A17 -> 28860
A13: Cr Cash | G13: =F12 -> 28860
A15: Purchase #2003
A16: Dr Inventory | F16: ='Working T Accounts'!A26 -> 29294.97
A17: Cr Cash | G17: =F16 -> 29294.97
A19: Purchase #1002
A20: Dr Inventory | F20: ='Working T Accounts'!A31 -> 31229.22
A21: Cr Accounts Payable | G21: =F20 -> 31229.22
